Workbook
Name AdminSubs: '🗂 Reference Data'!$C$2:$C$8
Name OfficeSubs: '🗂 Reference Data'!$D$2:$D$8
Name ProjectSubs: '🗂 Reference Data'!$B$2:$B$10

Sheet 📋 Instructions
B2: ⏱ WEEKLY TIMESHEET SYSTEM – EMPLOYEE GUIDE
B4: 🏢 ABOUT THIS WORKBOOK
B5: Purpose | C5: Record weekly working hours by project, category and sub-category. Timesheets must be submitted each week and approved by an Admin.
B6: Sheets included
B7: Who fills this? | C7: Every employee fills the '⏱ Weekly Timesheet' sheet. Admins use the '📁 Approval Log' to approve or decline entries.
B9: 📝 HOW TO FILL YOUR TIMESHEET – STEP BY STEP
B10: Step 1 – Employee Info | C10: Enter your name, employee ID and the week-start date (Monday) in the yellow cells at the top of the '⏱ Weekly Timesheet' sheet.
B11: Step 2 – Add a row per activity | C11: Each row = one activity. For each row fill: Date · Main Category · Sub-Category · Project No. (if Project category) · Hours · Description.
B12: Step 3 – Project Number format | C12: Project numbers follow [YYYY][3-digit sequence]: e.g. 2026101, 2026102 … 2026999. Leave blank for Admin or Office & Sales rows.
B13: Step 4 – TIL / Overtime usage | C13: To use accumulated TIL hours, select 'Admin' → 'Overtime Taken' and enter hours as a POSITIVE number (e.g. 8 for one day off) – system handles the deduction.
B14: Step 5 – Submit | C14: When your week is complete, use the Status dropdown in cell F5 and change it to 'Submitted'. A status banner at the bottom of the sheet will confirm your submission. Once submitted, notify your Admin to review and approve.
B15: Step 6 – Corrections | C15: If Admin declines your timesheet, the Status resets to 'Declined'. You may then edit and re-submit. Approved sheets cannot be edited.
B17: 📂 CATEGORIES QUICK REFERENCE
B18: PROJECT | C18: Travel · Site Travel · Site Work · Report · Extra Integration · Simulation · Office Preparation · Project Management · Engineering Work
B19: ADMIN | C19: Overtime Taken · TIL Payout · Sick Time · Annual Vacation · Statutory Holiday · Administrative · Toolbox Meeting
B20: OFFICE & SALES | C20: Customer Contact · Project Development · Proposals & Quotes · Inventory · SRU Study · Conference · General
B22: ⏰ OVERTIME & TIL RULES
B23: Overtime accrual | C23: Any hours logged ABOVE 8 hrs on a single day are automatically counted as overtime and added to your TIL bank.
B24: TIL Payout / Vacation | C24: Select Admin → 'Overtime Taken' and log hours (e.g. 8). This deducts from your TIL bank. The remaining balance shown in TIL Summary.
B25: TIL Payout (cash) | C25: If requesting a cash payout, select Admin → 'TIL Payout' wit hours. Payroll will process the amount.
B26: Balance carried forward | C26: Your overtime (hours > 8/day) is automatically calculated in the TIL Summary tab. The Opening Balance carries forward automatically each week — you do NOT need to re-enter it manually. Admin freezes the values after approving each week's timesheet.
B28: ✅ APPROVAL PROCESS
B29: Admin – Approve | C29: Open Approval Log, enter the employee name + week, set Status to 'Approved'. The timesheet is then locked permanently.
B30: Admin – Decline | C30: Set Status to 'Declined' in the Approval Log. Employee will see the status and can edit and re-submit.
B31: Audit trail | C31: Every status change is recorded in the Approval Log with date/time and approver name to prevent retroactive edits.
B33: ⚠️ IMPORTANT RULES
B34: No backdating | C34: Dates entered must be within the declared week range. The sheet highlights dates outside the week in red.
B35: Description required | C35: A description is mandatory for every row. Missing descriptions are highlighted in orange.
B36: One file per employee | C36: Each employee maintains their own copy of this file. Completed weeks are submitted to Admin for approval.

Sheet Weekly Timesheet
B2: ⏱ WEEKLY EMPLOYEE TIMESHEET
B4: Employee Name : | C4: Utsav Chovatia | E4: Week Starting : | F4: 46111
B5: Employee ID : | C5: 1 | E5: Status : | F5: Submitted
B6: Department : | C6: Engineering | E6: Approved By :
B7: Notes :
B9: Opening TIL (hrs) | D9: ='📊 TIL Summary'!C5 -> 843.25 | F9: Overtime Earned This Week | I9: =M30 -> 0 | K9: TIL Used / Remaining | M9: =D9+I9-N29 -> 823.25
B10: Opening Vacation (hrs) | D10: ='🏖 Vacation Summary'!C13 -> 48 | F10: Vacation Used This Week | I10: =SUMIF(C14:C28,"Vacation Hours",M14:M28) -> 0 | K10: Vacation Hours Remaining | M10: =D10-I10 -> 48
B12: Main Category | C12: Sub-Category | D12: Project No. | E12: Mon | F12: Tue | G12: Wed | H12: Thu | I12: Fri | J12: Sat | K12: Sun | L12: Task Description | M12: Total hrs | N12: Adj Overtime hrs
B13: Week of: | E13: =F4 -> 46111 | F13: =F4+1 -> 46112 | G13: =F4+2 -> 46113 | H13: =F4+3 -> 46114 | I13: =F4+4 -> 46115 | J13: =F4+5 -> 46116 | K13: =F4+6 -> 46117
B14: Admin | C14: TIL Payout | F14: 20 | L14: Recived Payment | M14: =IFERROR(SUM(E14:K14),0) -> 20 | N14: =IF(OR(C14="Overtime Taken", C14="TIL Payout"), M14, 0) -> 20
B15: Project | C15: Site Travel | D15: 2026125 | E15: 8 | L15: Travel to YYC | M15: =IFERROR(SUM(E15:K15),0) -> 8 | N15: =IF(OR(C15="Overtime Taken", C15="TIL Payout"), M15, 0) -> 0
B16: Admin | C16: Toolbox Meeting | G16: 1 | L16: Pit Stop | M16: =IFERROR(SUM(E16:K16),0) -> 1 | N16: =IF(OR(C16="Overtime Taken", C16="TIL Payout"), M16, 0) -> 0
B17: Office & Sales | C17: General | F17: 8 | G17: 7 | H17: 6 | L17: Timesheet; Email Reply; Timesheet and Expense report template for Team | M17: =IFERROR(SUM(E17:K17),0) -> 21 | N17: =IF(OR(C17="Overtime Taken", C17="TIL Payout"), M17, 0) -> 0
B18: Project | C18: Report | D18: 2026125 | H18: 2 | L18: Summary Letter | M18: =IFERROR(SUM(E18:K18),0) -> 2 | N18: =IF(OR(C18="Overtime Taken", C18="TIL Payout"), M18, 0) -> 0
B19: Admin | C19: Statutory Holiday | I19: 8 | L19: Good Friday | M19: =IFERROR(SUM(E19:K19),0) -> 8 | N19: =IF(OR(C19="Overtime Taken", C19="TIL Payout"), M19, 0) -> 0
M20: =IFERROR(SUM(E20:K20),0) -> 0 | N20: =IF(OR(C20="Overtime Taken", C20="TIL Payout"), M20, 0) -> 0
M21: =IFERROR(SUM(E21:K21),0) -> 0 | N21: =IF(OR(C21="Overtime Taken", C21="TIL Payout"), M21, 0) -> 0
M22: =IFERROR(SUM(E22:K22),0) -> 0 | N22: =IF(OR(C22="Overtime Taken", C22="TIL Payout"), M22, 0) -> 0
M23: =IFERROR(SUM(E23:K23),0) -> 0 | N23: =IF(OR(C23="Overtime Taken", C23="TIL Payout"), M23, 0) -> 0
M24: =IFERROR(SUM(E24:K24),0) -> 0 | N24: =IF(OR(C24="Overtime Taken", C24="TIL Payout"), M24, 0) -> 0
M25: =IFERROR(SUM(E25:K25),0) -> 0 | N25: =IF(OR(C25="Overtime Taken", C25="TIL Payout"), M25, 0) -> 0
M26: =IFERROR(SUM(E26:K26),0) -> 0 | N26: =IF(OR(C26="Overtime Taken", C26="TIL Payout"), M26, 0) -> 0
M27: =IFERROR(SUM(E27:K27),0) -> 0 | N27: =IF(OR(C27="Overtime Taken", C27="TIL Payout"), M27, 0) -> 0
M28: =IFERROR(SUM(E28:K28),0) -> 0 | N28: =IF(OR(C28="Overtime Taken", C28="TIL Payout"), M28, 0) -> 0
B29: Total Hours Worked | E29: =SUM(E14:E28) -> 8 | F29: =SUM(F14:F28) -> 28 | G29: =SUM(G14:G28) -> 8 | H29: =SUM(H14:H28) -> 8 | I29: =SUM(I14:I28) -> 8 | J29: =SUM(J14:J28) -> 0 | K29: =SUM(K14:K28) -> 0 | M29: =SUM(M14:M28) -> 60 | N29: =SUM(N14:N28) -> 20
B30: Overtime | E30: {=MAX(0, SUM(E14:E28) - 8 - SUM(SUMIFS(E14:E28, $C$14:$C$28, {"TIL Payout","Vacation Hours"})))} -> 0 | F30: {=MAX(0, SUM(F14:F28) - 8 - SUM(SUMIFS(F14:F28, $C$14:$C$28, {"TIL Payout","Vacation Hours"})))} -> 0 | G30: {=MAX(0, SUM(G14:G28) - 8 - SUM(SUMIFS(G14:G28, $C$14:$C$28, {"TIL Payout","Vacation Hours"})))} -> 0 | H30: {=MAX(0, SUM(H14:H28) - 8 - SUM(SUMIFS(H14:H28, $C$14:$C$28, {"TIL Payout","Vacation Hours"})))} -> 0 | I30: {=MAX(0, SUM(I14:I28) - 8 - SUM(SUMIFS(I14:I28, $C$14:$C$28, {"TIL Payout","Vacation Hours"})))} -> 0 | J30: =J29 -> 0 | K30: =K29 -> 0 | M30: =SUM(E30:K30) -> 0
B32: =IF(F5="Submitted","🔒 TIMESHEET SUBMITTED – Awaiting Admin Approval","📝 Status: "&F5&" – Change Status to 'Submitted' when your week is complete") -> 🔒 TIMESHEET SUBMITTED – Awaiting Admin Approval
B33: ⚠ Main Category determines Sub-Category options. Project No. required for 'Project' rows. Overtime Taken hours auto-move to Adj Overtime column. Vacation Hours auto-deduct from Vacation balance.

Sheet 📄 Weekly Report
B2: 📄 WEEKLY TIMESHEET REPORT · Sulfur Recovery Engineering Inc.
B4: Employee Name | E4: ='Weekly Timesheet'!C4 -> Utsav Chovatia | N4: Week Starting | P4: ='Weekly Timesheet'!F4 -> 46111
B5: Employee ID | E5: ='Weekly Timesheet'!C5 -> 1 | N5: Status | P5: ='Weekly Timesheet'!F5 -> Submitted
B6: Department | E6: ='Weekly Timesheet'!C6 -> Engineering | N6: Approved By | P6: ='Weekly Timesheet'!F6 -> 0
B7: Report Generated | E7: =TEXT(TODAY(),"DD MMMM YYYY") -> 18 June 2026
B9: WEEK AT A GLANCE
B10: =IFERROR(SUM('Weekly Timesheet'!$M$14:$M$28),0) -> 60 | F10: ='Weekly Timesheet'!I9 -> 0 | J10: ='Weekly Timesheet'!M9 -> 823.25 | O10: ='Weekly Timesheet'!M10 -> 48 | S10: =IFERROR(SUMIF('Weekly Timesheet'!$B$14:$B$28,"Project",'Weekly Timesheet'!$M$14:$M$28),0) -> 10
B11: Total Hours Logged | F11: Overtime Earned | J11: TIL Bank Remaining | O11: Vacation Hrs Remaining | S11: Project Hours This Week
B13: DAILY HOURS BREAKDOWN | N13: HOURS BY CATEGORY
B15: Category | E15: Mon | F15: Tue | G15: Wed | H15: Thu | I15: Fri | J15: Sat | K15: Sun | L15: Week Total | N15: Category | Q15: Total Hours | V15: % of Week Total
B16: Regular Hours | E16: =IFERROR(SUM('Weekly Timesheet'!E14:E28)-MAX(0,SUM('Weekly Timesheet'!E14:E28)-8),0) -> 8 | F16: =IFERROR(SUM('Weekly Timesheet'!F14:F28)-MAX(0,SUM('Weekly Timesheet'!F14:F28)-8),0) -> 8 | G16: =IFERROR(SUM('Weekly Timesheet'!G14:G28)-MAX(0,SUM('Weekly Timesheet'!G14:G28)-8),0) -> 8 | H16: =IFERROR(SUM('Weekly Timesheet'!H14:H28)-MAX(0,SUM('Weekly Timesheet'!H14:H28)-8),0) -> 8 | I16: =IFERROR(SUM('Weekly Timesheet'!I14:I28)-MAX(0,SUM('Weekly Timesheet'!I14:I28)-8),0) -> 8 | J16: 0 | K16: 0 | L16: =SUM(E16:K16) -> 40 | N16: Project | Q16: =IFERROR(SUMIF('Weekly Timesheet'!$B$14:$B$28,"Project",'Weekly Timesheet'!$M$14:$M$28),0) -> 10 | V16: =IFERROR(Q16/Q19,0) -> 0.16666667
B17: Overtime | E17: =IFERROR(MAX(0, SUMIFS('Weekly Timesheet'!E14:E28, 'Weekly Timesheet'!$C$14:$C$28, "<>TIL Payout") - 8), 0) -> 0 | F17: =IFERROR(MAX(0, SUMIFS('Weekly Timesheet'!F14:F28, 'Weekly Timesheet'!$C$14:$C$28, "<>TIL Payout") - 8), 0) -> 0 | G17: =IFERROR(MAX(0, SUMIFS('Weekly Timesheet'!G14:G28, 'Weekly Timesheet'!$C$14:$C$28, "<>TIL Payout") - 8), 0) -> 0 | H17: =IFERROR(MAX(0, SUMIFS('Weekly Timesheet'!H14:H28, 'Weekly Timesheet'!$C$14:$C$28, "<>TIL Payout") - 8), 0) -> 0 | I17: =IFERROR(MAX(0, SUMIFS('Weekly Timesheet'!I14:I28, 'Weekly Timesheet'!$C$14:$C$28, "<>TIL Payout") - 8), 0) -> 0 | J17: =SUM('Weekly Timesheet'!J14:J28) -> 0 | K17: =SUM('Weekly Timesheet'!K14:K28) -> 0 | L17: =SUM(E17:K17) -> 0 | N17: Admin | Q17: =IFERROR(SUMIF('Weekly Timesheet'!$B$14:$B$28,"Admin",'Weekly Timesheet'!$M$14:$M$28),0) -> 29 | V17: =IFERROR(Q17/Q19,0) -> 0.48333333
B18: TIL Payout | E18: =IFERROR(SUMIFS('Weekly Timesheet'!E14:E28, 'Weekly Timesheet'!$C$14:$C$28, "TIL Payout"), 0) -> 0 | F18: =IFERROR(SUMIFS('Weekly Timesheet'!F14:F28, 'Weekly Timesheet'!$C$14:$C$28, "TIL Payout"), 0) -> 20 | G18: =IFERROR(SUMIFS('Weekly Timesheet'!G14:G28, 'Weekly Timesheet'!$C$14:$C$28, "TIL Payout"), 0) -> 0 | H18: =IFERROR(SUMIFS('Weekly Timesheet'!H14:H28, 'Weekly Timesheet'!$C$14:$C$28, "TIL Payout"), 0) -> 0 | I18: =IFERROR(SUMIFS('Weekly Timesheet'!I14:I28, 'Weekly Timesheet'!$C$14:$C$28, "TIL Payout"), 0) -> 0 | J18: =IFERROR(SUMIFS('Weekly Timesheet'!J14:J28, 'Weekly Timesheet'!$C$14:$C$28, "TIL Payout"), 0) -> 0 | K18: =IFERROR(SUMIFS('Weekly Timesheet'!K14:K28, 'Weekly Timesheet'!$C$14:$C$28, "TIL Payout"), 0) -> 0 | L18: =SUM(E18:K18) -> 20 | N18: Office & Sales | Q18: =IFERROR(SUMIF('Weekly Timesheet'!$B$14:$B$28,"Office & Sales",'Weekly Timesheet'!$M$14:$M$28),0) -> 21 | V18: =IFERROR(Q18/Q19,0) -> 0.35
B19: Total Hours | E19: =IFERROR(SUM('Weekly Timesheet'!E14:E28),0) -> 8 | F19: =IFERROR(SUM('Weekly Timesheet'!F14:F28),0) -> 28 | G19: =IFERROR(SUM('Weekly Timesheet'!G14:G28),0) -> 8 | H19: =IFERROR(SUM('Weekly Timesheet'!H14:H28),0) -> 8 | I19: =IFERROR(SUM('Weekly Timesheet'!I14:I28),0) -> 8 | J19: =IFERROR(SUM('Weekly Timesheet'!J14:J28),0) -> 0 | K19: =IFERROR(SUM('Weekly Timesheet'!K14:K28),0) -> 0 | L19: =SUM(E19:K19) -> 60 | N19: TOTAL | Q19: =IFERROR(SUM('Weekly Timesheet'!$M$14:$M$28),0) -> 60 | V19: 1
B21: HOURS BY SUB-CATEGORY | N21: HOURS BY PROJECT NUMBER
B23: Main Category | D23: Sub-Category | H23: Hours | K23: % of Category | N23: Project No. | P23: Sub-Category | Q23: Mon | R23: Tue | S23: Wed | T23: Thu | U23: Fri | V23: Sat | W23: Total hrs
B24: Project | D24: Travel | H24: =IFERROR(SUMIFS('Weekly Timesheet'!$M$14:$M$28,'Weekly Timesheet'!$B$14:$B$28,"Project",'Weekly Timesheet'!$C$14:$C$28,"Travel"),0) -> 0 | K24: =IFERROR(H24/SUMIF('Weekly Timesheet'!$B$14:$B$28,"Project",'Weekly Timesheet'!$M$14:$M$28),0) -> 0 | N24: {=IFERROR(INDEX(_xlfn._xlws.SORT(_xlfn.UNIQUE(_xlfn._xlws.FILTER('Weekly Timesheet'!$D$14:$D$28,'Weekly Timesheet'!$B$14:$B$28="Project"))),1,1),"")} -> 2026125 | P24: {=IFERROR(IF(N24="","",INDEX('Weekly Timesheet'!$C$14:$C$28,MATCH(1,('Weekly Timesheet'!$B$14:$B$28="Project")*('Weekly Timesheet'!$D$14:$D$28=N24),0))),"")} -> Site Travel | Q24: =IFERROR(IF(N24="","",SUMIFS('Weekly Timesheet'!$E$14:$E$28,'Weekly Timesheet'!$B$14:$B$28,"Project",'Weekly Timesheet'!$D$14:$D$28,N24)),"") -> 8 | R24: =IFERROR(IF(N24="","",SUMIFS('Weekly Timesheet'!$F$14:$F$28,'Weekly Timesheet'!$B$14:$B$28,"Project",'Weekly Timesheet'!$D$14:$D$28,N24)),"") -> 0 | S24: =IFERROR(IF(N24="","",SUMIFS('Weekly Timesheet'!$G$14:$G$28,'Weekly Timesheet'!$B$14:$B$28,"Project",'Weekly Timesheet'!$D$14:$D$28,N24)),"") -> 0 | T24: =IFERROR(IF(N24="","",SUMIFS('Weekly Timesheet'!$H$14:$H$28,'Weekly Timesheet'!$B$14:$B$28,"Project",'Weekly Timesheet'!$D$14:$D$28,N24)),"") -> 2 | U24: =IFERROR(IF(N24="","",SUMIFS('Weekly Timesheet'!$I$14:$I$28,'Weekly Timesheet'!$B$14:$B$28,"Project",'Weekly Timesheet'!$D$14:$D$28,N24)),"") -> 0 | V24: =IFERROR(IF(N24="","",SUMIFS('Weekly Timesheet'!$J$14:$J$28,'Weekly Timesheet'!$B$14:$B$28,"Project",'Weekly Timesheet'!$D$14:$D$28,N24)),"") -> 0 | W24: =IFERROR(IF(N24="","",SUMIFS('Weekly Timesheet'!$M$14:$M$28,'Weekly Timesheet'!$B$14:$B$28,"Project",'Weekly Timesheet'!$D$14:$D$28,N24)),"") -> 10
D25: Site Travel | H25: =IFERROR(SUMIFS('Weekly Timesheet'!$M$14:$M$28,'Weekly Timesheet'!$B$14:$B$28,"Project",'Weekly Timesheet'!$C$14:$C$28,"Site Travel"),0) -> 8 | K25: =IFERROR(H25/SUMIF('Weekly Timesheet'!$B$14:$B$28,"Project",'Weekly Timesheet'!$M$14:$M$28),0) -> 0.8 | N25: {=IFERROR(INDEX(_xlfn._xlws.SORT(_xlfn.UNIQUE(_xlfn._xlws.FILTER('Weekly Timesheet'!$D$14:$D$28,'Weekly Timesheet'!$B$14:$B$28="Project"))),2,1),"")} | P25: {=IFERROR(IF(N25="","",INDEX('Weekly Timesheet'!$C$14:$C$28,MATCH(1,('Weekly Timesheet'!$B$14:$B$28="Project")*('Weekly Timesheet'!$D$14:$D$28=N25),0))),"")} | Q25: =IFERROR(IF(N25="","",SUMIFS('Weekly Timesheet'!$E$14:$E$28,'Weekly Timesheet'!$B$14:$B$28,"Project",'Weekly Timesheet'!$D$14:$D$28,N25)),"") | R25: =IFERROR(IF(N25="","",SUMIFS('Weekly Timesheet'!$F$14:$F$28,'Weekly Timesheet'!$B$14:$B$28,"Project",'Weekly Timesheet'!$D$14:$D$28,N25)),"") | S25: =IFERROR(IF(N25="","",SUMIFS('Weekly Timesheet'!$G$14:$G$28,'Weekly Timesheet'!$B$14:$B$28,"Project",'Weekly Timesheet'!$D$14:$D$28,N25)),"") | T25: =IFERROR(IF(N25="","",SUMIFS('Weekly Timesheet'!$H$14:$H$28,'Weekly Timesheet'!$B$14:$B$28,"Project",'Weekly Timesheet'!$D$14:$D$28,N25)),"") | U25: =IFERROR(IF(N25="","",SUMIFS('Weekly Timesheet'!$I$14:$I$28,'Weekly Timesheet'!$B$14:$B$28,"Project",'Weekly Timesheet'!$D$14:$D$28,N25)),"") | V25: =IFERROR(IF(N25="","",SUMIFS('Weekly Timesheet'!$J$14:$J$28,'Weekly Timesheet'!$B$14:$B$28,"Project",'Weekly Timesheet'!$D$14:$D$28,N25)),"") | W25: =IFERROR(IF(N25="","",SUMIFS('Weekly Timesheet'!$M$14:$M$28,'Weekly Timesheet'!$B$14:$B$28,"Project",'Weekly Timesheet'!$D$14:$D$28,N25)),"")
D26: Site Work | H26: =IFERROR(SUMIFS('Weekly Timesheet'!$M$14:$M$28,'Weekly Timesheet'!$B$14:$B$28,"Project",'Weekly Timesheet'!$C$14:$C$28,"Site Work"),0) -> 0 | K26: =IFERROR(H26/SUMIF('Weekly Timesheet'!$B$14:$B$28,"Project",'Weekly Timesheet'!$M$14:$M$28),0) -> 0 | N26: {=IFERROR(INDEX(_xlfn._xlws.SORT(_xlfn.UNIQUE(_xlfn._xlws.FILTER('Weekly Timesheet'!$D$14:$D$28,'Weekly Timesheet'!$B$14:$B$28="Project"))),3,1),"")} | P26: {=IFERROR(IF(N26="","",INDEX('Weekly Timesheet'!$C$14:$C$28,MATCH(1,('Weekly Timesheet'!$B$14:$B$28="Project")*('Weekly Timesheet'!$D$14:$D$28=N26),0))),"")} | Q26: =IFERROR(IF(N26="","",SUMIFS('Weekly Timesheet'!$E$14:$E$28,'Weekly Timesheet'!$B$14:$B$28,"Project",'Weekly Timesheet'!$D$14:$D$28,N26)),"") | R26: =IFERROR(IF(N26="","",SUMIFS('Weekly Timesheet'!$F$14:$F$28,'Weekly Timesheet'!$B$14:$B$28,"Project",'Weekly Timesheet'!$D$14:$D$28,N26)),"") | S26: =IFERROR(IF(N26="","",SUMIFS('Weekly Timesheet'!$G$14:$G$28,'Weekly Timesheet'!$B$14:$B$28,"Project",'Weekly Timesheet'!$D$14:$D$28,N26)),"") | T26: =IFERROR(IF(N26="","",SUMIFS('Weekly Timesheet'!$H$14:$H$28,'Weekly Timesheet'!$B$14:$B$28,"Project",'Weekly Timesheet'!$D$14:$D$28,N26)),"") | U26: =IFERROR(IF(N26="","",SUMIFS('Weekly Timesheet'!$I$14:$I$28,'Weekly Timesheet'!$B$14:$B$28,"Project",'Weekly Timesheet'!$D$14:$D$28,N26)),"") | V26: =IFERROR(IF(N26="","",SUMIFS('Weekly Timesheet'!$J$14:$J$28,'Weekly Timesheet'!$B$14:$B$28,"Project",'Weekly Timesheet'!$D$14:$D$28,N26)),"") | W26: =IFERROR(IF(N26="","",SUMIFS('Weekly Timesheet'!$M$14:$M$28,'Weekly Timesheet'!$B$14:$B$28,"Project",'Weekly Timesheet'!$D$14:$D$28,N26)),"")
D27: Report | H27: =IFERROR(SUMIFS('Weekly Timesheet'!$M$14:$M$28,'Weekly Timesheet'!$B$14:$B$28,"Project",'Weekly Timesheet'!$C$14:$C$28,"Report"),0) -> 2 | K27: =IFERROR(H27/SUMIF('Weekly Timesheet'!$B$14:$B$28,"Project",'Weekly Timesheet'!$M$14:$M$28),0) -> 0.2 | N27: {=IFERROR(INDEX(_xlfn._xlws.SORT(_xlfn.UNIQUE(_xlfn._xlws.FILTER('Weekly Timesheet'!$D$14:$D$28,'Weekly Timesheet'!$B$14:$B$28="Project"))),4,1),"")} | P27: {=IFERROR(IF(N27="","",INDEX('Weekly Timesheet'!$C$14:$C$28,MATCH(1,('Weekly Timesheet'!$B$14:$B$28="Project")*('Weekly Timesheet'!$D$14:$D$28=N27),0))),"")} | Q27: =IFERROR(IF(N27="","",SUMIFS('Weekly Timesheet'!$E$14:$E$28,'Weekly Timesheet'!$B$14:$B$28,"Project",'Weekly Timesheet'!$D$14:$D$28,N27)),"") | R27: =IFERROR(IF(N27="","",SUMIFS('Weekly Timesheet'!$F$14:$F$28,'Weekly Timesheet'!$B$14:$B$28,"Project",'Weekly Timesheet'!$D$14:$D$28,N27)),"") | S27: =IFERROR(IF(N27="","",SUMIFS('Weekly Timesheet'!$G$14:$G$28,'Weekly Timesheet'!$B$14:$B$28,"Project",'Weekly Timesheet'!$D$14:$D$28,N27)),"") | T27: =IFERROR(IF(N27="","",SUMIFS('Weekly Timesheet'!$H$14:$H$28,'Weekly Timesheet'!$B$14:$B$28,"Project",'Weekly Timesheet'!$D$14:$D$28,N27)),"") | U27: =IFERROR(IF(N27="","",SUMIFS('Weekly Timesheet'!$I$14:$I$28,'Weekly Timesheet'!$B$14:$B$28,"Project",'Weekly Timesheet'!$D$14:$D$28,N27)),"") | V27: =IFERROR(IF(N27="","",SUMIFS('Weekly Timesheet'!$J$14:$J$28,'Weekly Timesheet'!$B$14:$B$28,"Project",'Weekly Timesheet'!$D$14:$D$28,N27)),"") | W27: =IFERROR(IF(N27="","",SUMIFS('Weekly Timesheet'!$M$14:$M$28,'Weekly Timesheet'!$B$14:$B$28,"Project",'Weekly Timesheet'!$D$14:$D$28,N27)),"")
D28: Extra Integration | H28: =IFERROR(SUMIFS('Weekly Timesheet'!$M$14:$M$28,'Weekly Timesheet'!$B$14:$B$28,"Project",'Weekly Timesheet'!$C$14:$C$28,"Extra Integration"),0) -> 0 | K28: =IFERROR(H28/SUMIF('Weekly Timesheet'!$B$14:$B$28,"Project",'Weekly Timesheet'!$M$14:$M$28),0) -> 0 | N28: {=IFERROR(INDEX(_xlfn._xlws.SORT(_xlfn.UNIQUE(_xlfn._xlws.FILTER('Weekly Timesheet'!$D$14:$D$28,'Weekly Timesheet'!$B$14:$B$28="Project"))),5,1),"")} | P28: {=IFERROR(IF(N28="","",INDEX('Weekly Timesheet'!$C$14:$C$28,MATCH(1,('Weekly Timesheet'!$B$14:$B$28="Project")*('Weekly Timesheet'!$D$14:$D$28=N28),0))),"")} | Q28: =IFERROR(IF(N28="","",SUMIFS('Weekly Timesheet'!$E$14:$E$28,'Weekly Timesheet'!$B$14:$B$28,"Project",'Weekly Timesheet'!$D$14:$D$28,N28)),"") | R28: =IFERROR(IF(N28="","",SUMIFS('Weekly Timesheet'!$F$14:$F$28,'Weekly Timesheet'!$B$14:$B$28,"Project",'Weekly Timesheet'!$D$14:$D$28,N28)),"") | S28: =IFERROR(IF(N28="","",SUMIFS('Weekly Timesheet'!$G$14:$G$28,'Weekly Timesheet'!$B$14:$B$28,"Project",'Weekly Timesheet'!$D$14:$D$28,N28)),"") | T28: =IFERROR(IF(N28="","",SUMIFS('Weekly Timesheet'!$H$14:$H$28,'Weekly Timesheet'!$B$14:$B$28,"Project",'Weekly Timesheet'!$D$14:$D$28,N28)),"") | U28: =IFERROR(IF(N28="","",SUMIFS('Weekly Timesheet'!$I$14:$I$28,'Weekly Timesheet'!$B$14:$B$28,"Project",'Weekly Timesheet'!$D$14:$D$28,N28)),"") | V28: =IFERROR(IF(N28="","",SUMIFS('Weekly Timesheet'!$J$14:$J$28,'Weekly Timesheet'!$B$14:$B$28,"Project",'Weekly Timesheet'!$D$14:$D$28,N28)),"") | W28: =IFERROR(IF(N28="","",SUMIFS('Weekly Timesheet'!$M$14:$M$28,'Weekly Timesheet'!$B$14:$B$28,"Project",'Weekly Timesheet'!$D$14:$D$28,N28)),"")
D29: Simulation | H29: =IFERROR(SUMIFS('Weekly Timesheet'!$M$14:$M$28,'Weekly Timesheet'!$B$14:$B$28,"Project",'Weekly Timesheet'!$C$14:$C$28,"Simulation"),0) -> 0 | K29: =IFERROR(H29/SUMIF('Weekly Timesheet'!$B$14:$B$28,"Project",'Weekly Timesheet'!$M$14:$M$28),0) -> 0 | N29: {=IFERROR(INDEX(_xlfn._xlws.SORT(_xlfn.UNIQUE(_xlfn._xlws.FILTER('Weekly Timesheet'!$D$14:$D$28,'Weekly Timesheet'!$B$14:$B$28="Project"))),6,1),"")} | P29: {=IFERROR(IF(N29="","",INDEX('Weekly Timesheet'!$C$14:$C$28,MATCH(1,('Weekly Timesheet'!$B$14:$B$28="Project")*('Weekly Timesheet'!$D$14:$D$28=N29),0))),"")} | Q29: =IFERROR(IF(N29="","",SUMIFS('Weekly Timesheet'!$E$14:$E$28,'Weekly Timesheet'!$B$14:$B$28,"Project",'Weekly Timesheet'!$D$14:$D$28,N29)),"") | R29: =IFERROR(IF(N29="","",SUMIFS('Weekly Timesheet'!$F$14:$F$28,'Weekly Timesheet'!$B$14:$B$28,"Project",'Weekly Timesheet'!$D$14:$D$28,N29)),"") | S29: =IFERROR(IF(N29="","",SUMIFS('Weekly Timesheet'!$G$14:$G$28,'Weekly Timesheet'!$B$14:$B$28,"Project",'Weekly Timesheet'!$D$14:$D$28,N29)),"") | T29: =IFERROR(IF(N29="","",SUMIFS('Weekly Timesheet'!$H$14:$H$28,'Weekly Timesheet'!$B$14:$B$28,"Project",'Weekly Timesheet'!$D$14:$D$28,N29)),"") | U29: =IFERROR(IF(N29="","",SUMIFS('Weekly Timesheet'!$I$14:$I$28,'Weekly Timesheet'!$B$14:$B$28,"Project",'Weekly Timesheet'!$D$14:$D$28,N29)),"") | V29: =IFERROR(IF(N29="","",SUMIFS('Weekly Timesheet'!$J$14:$J$28,'Weekly Timesheet'!$B$14:$B$28,"Project",'Weekly Timesheet'!$D$14:$D$28,N29)),"") | W29: =IFERROR(IF(N29="","",SUMIFS('Weekly Timesheet'!$M$14:$M$28,'Weekly Timesheet'!$B$14:$B$28,"Project",'Weekly Timesheet'!$D$14:$D$28,N29)),"")
D30: Office Preparation | H30: =IFERROR(SUMIFS('Weekly Timesheet'!$M$14:$M$28,'Weekly Timesheet'!$B$14:$B$28,"Project",'Weekly Timesheet'!$C$14:$C$28,"Office Preparation"),0) -> 0 | K30: =IFERROR(H30/SUMIF('Weekly Timesheet'!$B$14:$B$28,"Project",'Weekly Timesheet'!$M$14:$M$28),0) -> 0 | N30: {=IFERROR(INDEX(_xlfn._xlws.SORT(_xlfn.UNIQUE(_xlfn._xlws.FILTER('Weekly Timesheet'!$D$14:$D$28,'Weekly Timesheet'!$B$14:$B$28="Project"))),7,1),"")} | P30: {=IFERROR(IF(N30="","",INDEX('Weekly Timesheet'!$C$14:$C$28,MATCH(1,('Weekly Timesheet'!$B$14:$B$28="Project")*('Weekly Timesheet'!$D$14:$D$28=N30),0))),"")} | Q30: =IFERROR(IF(N30="","",SUMIFS('Weekly Timesheet'!$E$14:$E$28,'Weekly Timesheet'!$B$14:$B$28,"Project",'Weekly Timesheet'!$D$14:$D$28,N30)),"") | R30: =IFERROR(IF(N30="","",SUMIFS('Weekly Timesheet'!$F$14:$F$28,'Weekly Timesheet'!$B$14:$B$28,"Project",'Weekly Timesheet'!$D$14:$D$28,N30)),"") | S30: =IFERROR(IF(N30="","",SUMIFS('Weekly Timesheet'!$G$14:$G$28,'Weekly Timesheet'!$B$14:$B$28,"Project",'Weekly Timesheet'!$D$14:$D$28,N30)),"") | T30: =IFERROR(IF(N30="","",SUMIFS('Weekly Timesheet'!$H$14:$H$28,'Weekly Timesheet'!$B$14:$B$28,"Project",'Weekly Timesheet'!$D$14:$D$28,N30)),"") | U30: =IFERROR(IF(N30="","",SUMIFS('Weekly Timesheet'!$I$14:$I$28,'Weekly Timesheet'!$B$14:$B$28,"Project",'Weekly Timesheet'!$D$14:$D$28,N30)),"") | V30: =IFERROR(IF(N30="","",SUMIFS('Weekly Timesheet'!$J$14:$J$28,'Weekly Timesheet'!$B$14:$B$28,"Project",'Weekly Timesheet'!$D$14:$D$28,N30)),"") | W30: =IFERROR(IF(N30="","",SUMIFS('Weekly Timesheet'!$M$14:$M$28,'Weekly Timesheet'!$B$14:$B$28,"Project",'Weekly Timesheet'!$D$14:$D$28,N30)),"")
D31: Project Management | H31: =IFERROR(SUMIFS('Weekly Timesheet'!$M$14:$M$28,'Weekly Timesheet'!$B$14:$B$28,"Project",'Weekly Timesheet'!$C$14:$C$28,"Project Management"),0) -> 0 | K31: =IFERROR(H31/SUMIF('Weekly Timesheet'!$B$14:$B$28,"Project",'Weekly Timesheet'!$M$14:$M$28),0) -> 0 | N31: {=IFERROR(INDEX(_xlfn._xlws.SORT(_xlfn.UNIQUE(_xlfn._xlws.FILTER('Weekly Timesheet'!$D$14:$D$28,'Weekly Timesheet'!$B$14:$B$28="Project"))),8,1),"")} | P31: {=IFERROR(IF(N31="","",INDEX('Weekly Timesheet'!$C$14:$C$28,MATCH(1,('Weekly Timesheet'!$B$14:$B$28="Project")*('Weekly Timesheet'!$D$14:$D$28=N31),0))),"")} | Q31: =IFERROR(IF(N31="","",SUMIFS('Weekly Timesheet'!$E$14:$E$28,'Weekly Timesheet'!$B$14:$B$28,"Project",'Weekly Timesheet'!$D$14:$D$28,N31)),"") | R31: =IFERROR(IF(N31="","",SUMIFS('Weekly Timesheet'!$F$14:$F$28,'Weekly Timesheet'!$B$14:$B$28,"Project",'Weekly Timesheet'!$D$14:$D$28,N31)),"") | S31: =IFERROR(IF(N31="","",SUMIFS('Weekly Timesheet'!$G$14:$G$28,'Weekly Timesheet'!$B$14:$B$28,"Project",'Weekly Timesheet'!$D$14:$D$28,N31)),"") | T31: =IFERROR(IF(N31="","",SUMIFS('Weekly Timesheet'!$H$14:$H$28,'Weekly Timesheet'!$B$14:$B$28,"Project",'Weekly Timesheet'!$D$14:$D$28,N31)),"") | U31: =IFERROR(IF(N31="","",SUMIFS('Weekly Timesheet'!$I$14:$I$28,'Weekly Timesheet'!$B$14:$B$28,"Project",'Weekly Timesheet'!$D$14:$D$28,N31)),"") | V31: =IFERROR(IF(N31="","",SUMIFS('Weekly Timesheet'!$J$14:$J$28,'Weekly Timesheet'!$B$14:$B$28,"Project",'Weekly Timesheet'!$D$14:$D$28,N31)),"") | W31: =IFERROR(IF(N31="","",SUMIFS('Weekly Timesheet'!$M$14:$M$28,'Weekly Timesheet'!$B$14:$B$28,"Project",'Weekly Timesheet'!$D$14:$D$28,N31)),"")
D32: Engineering Work | H32: =IFERROR(SUMIFS('Weekly Timesheet'!$M$14:$M$28,'Weekly Timesheet'!$B$14:$B$28,"Project",'Weekly Timesheet'!$C$14:$C$28,"Engineering Work"),0) -> 0 | K32: =IFERROR(H32/SUMIF('Weekly Timesheet'!$B$14:$B$28,"Project",'Weekly Timesheet'!$M$14:$M$28),0) -> 0 | N32: {=IFERROR(INDEX(_xlfn._xlws.SORT(_xlfn.UNIQUE(_xlfn._xlws.FILTER('Weekly Timesheet'!$D$14:$D$28,'Weekly Timesheet'!$B$14:$B$28="Project"))),9,1),"")} | P32: {=IFERROR(IF(N32="","",INDEX('Weekly Timesheet'!$C$14:$C$28,MATCH(1,('Weekly Timesheet'!$B$14:$B$28="Project")*('Weekly Timesheet'!$D$14:$D$28=N32),0))),"")} | Q32: =IFERROR(IF(N32="","",SUMIFS('Weekly Timesheet'!$E$14:$E$28,'Weekly Timesheet'!$B$14:$B$28,"Project",'Weekly Timesheet'!$D$14:$D$28,N32)),"") | R32: =IFERROR(IF(N32="","",SUMIFS('Weekly Timesheet'!$F$14:$F$28,'Weekly Timesheet'!$B$14:$B$28,"Project",'Weekly Timesheet'!$D$14:$D$28,N32)),"") | S32: =IFERROR(IF(N32="","",SUMIFS('Weekly Timesheet'!$G$14:$G$28,'Weekly Timesheet'!$B$14:$B$28,"Project",'Weekly Timesheet'!$D$14:$D$28,N32)),"") | T32: =IFERROR(IF(N32="","",SUMIFS('Weekly Timesheet'!$H$14:$H$28,'Weekly Timesheet'!$B$14:$B$28,"Project",'Weekly Timesheet'!$D$14:$D$28,N32)),"") | U32: =IFERROR(IF(N32="","",SUMIFS('Weekly Timesheet'!$I$14:$I$28,'Weekly Timesheet'!$B$14:$B$28,"Project",'Weekly Timesheet'!$D$14:$D$28,N32)),"") | V32: =IFERROR(IF(N32="","",SUMIFS('Weekly Timesheet'!$J$14:$J$28,'Weekly Timesheet'!$B$14:$B$28,"Project",'Weekly Timesheet'!$D$14:$D$28,N32)),"") | W32: =IFERROR(IF(N32="","",SUMIFS('Weekly Timesheet'!$M$14:$M$28,'Weekly Timesheet'!$B$14:$B$28,"Project",'Weekly Timesheet'!$D$14:$D$28,N32)),"")
B33: Admin | D33: Overtime Taken | H33: =IFERROR(SUMIFS('Weekly Timesheet'!$M$14:$M$28,'Weekly Timesheet'!$B$14:$B$28,"Admin",'Weekly Timesheet'!$C$14:$C$28,"Overtime Taken"),0) -> 0 | K33: =IFERROR(H33/SUMIF('Weekly Timesheet'!$B$14:$B$28,"Admin",'Weekly Timesheet'!$M$14:$M$28),0) -> 0 | N33: {=IFERROR(INDEX(_xlfn._xlws.SORT(_xlfn.UNIQUE(_xlfn._xlws.FILTER('Weekly Timesheet'!$D$14:$D$28,'Weekly Timesheet'!$B$14:$B$28="Project"))),10,1),"")} | P33: {=IFERROR(IF(N33="","",INDEX('Weekly Timesheet'!$C$14:$C$28,MATCH(1,('Weekly Timesheet'!$B$14:$B$28="Project")*('Weekly Timesheet'!$D$14:$D$28=N33),0))),"")} | Q33: =IFERROR(IF(N33="","",SUMIFS('Weekly Timesheet'!$E$14:$E$28,'Weekly Timesheet'!$B$14:$B$28,"Project",'Weekly Timesheet'!$D$14:$D$28,N33)),"") | R33: =IFERROR(IF(N33="","",SUMIFS('Weekly Timesheet'!$F$14:$F$28,'Weekly Timesheet'!$B$14:$B$28,"Project",'Weekly Timesheet'!$D$14:$D$28,N33)),"") | S33: =IFERROR(IF(N33="","",SUMIFS('Weekly Timesheet'!$G$14:$G$28,'Weekly Timesheet'!$B$14:$B$28,"Project",'Weekly Timesheet'!$D$14:$D$28,N33)),"") | T33: =IFERROR(IF(N33="","",SUMIFS('Weekly Timesheet'!$H$14:$H$28,'Weekly Timesheet'!$B$14:$B$28,"Project",'Weekly Timesheet'!$D$14:$D$28,N33)),"") | U33: =IFERROR(IF(N33="","",SUMIFS('Weekly Timesheet'!$I$14:$I$28,'Weekly Timesheet'!$B$14:$B$28,"Project",'Weekly Timesheet'!$D$14:$D$28,N33)),"") | V33: =IFERROR(IF(N33="","",SUMIFS('Weekly Timesheet'!$J$14:$J$28,'Weekly Timesheet'!$B$14:$B$28,"Project",'Weekly Timesheet'!$D$14:$D$28,N33)),"") | W33: =IFERROR(IF(N33="","",SUMIFS('Weekly Timesheet'!$M$14:$M$28,'Weekly Timesheet'!$B$14:$B$28,"Project",'Weekly Timesheet'!$D$14:$D$28,N33)),"")
D34: TIL Payout | H34: =IFERROR(SUMIFS('Weekly Timesheet'!$M$14:$M$28,'Weekly Timesheet'!$B$14:$B$28,"Admin",'Weekly Timesheet'!$C$14:$C$28,"TIL Payout"),0) -> 20 | K34: =IFERROR(H34/SUMIF('Weekly Timesheet'!$B$14:$B$28,"Admin",'Weekly Timesheet'!$M$14:$M$28),0) -> 0.68965517 | N34: {=IFERROR(INDEX(_xlfn._xlws.SORT(_xlfn.UNIQUE(_xlfn._xlws.FILTER('Weekly Timesheet'!$D$14:$D$28,'Weekly Timesheet'!$B$14:$B$28="Project"))),11,1),"")} | P34: {=IFERROR(IF(N34="","",INDEX('Weekly Timesheet'!$C$14:$C$28,MATCH(1,('Weekly Timesheet'!$B$14:$B$28="Project")*('Weekly Timesheet'!$D$14:$D$28=N34),0))),"")} | Q34: =IFERROR(IF(N34="","",SUMIFS('Weekly Timesheet'!$E$14:$E$28,'Weekly Timesheet'!$B$14:$B$28,"Project",'Weekly Timesheet'!$D$14:$D$28,N34)),"") | R34: =IFERROR(IF(N34="","",SUMIFS('Weekly Timesheet'!$F$14:$F$28,'Weekly Timesheet'!$B$14:$B$28,"Project",'Weekly Timesheet'!$D$14:$D$28,N34)),"") | S34: =IFERROR(IF(N34="","",SUMIFS('Weekly Timesheet'!$G$14:$G$28,'Weekly Timesheet'!$B$14:$B$28,"Project",'Weekly Timesheet'!$D$14:$D$28,N34)),"") | T34: =IFERROR(IF(N34="","",SUMIFS('Weekly Timesheet'!$H$14:$H$28,'Weekly Timesheet'!$B$14:$B$28,"Project",'Weekly Timesheet'!$D$14:$D$28,N34)),"") | U34: =IFERROR(IF(N34="","",SUMIFS('Weekly Timesheet'!$I$14:$I$28,'Weekly Timesheet'!$B$14:$B$28,"Project",'Weekly Timesheet'!$D$14:$D$28,N34)),"") | V34: =IFERROR(IF(N34="","",SUMIFS('Weekly Timesheet'!$J$14:$J$28,'Weekly Timesheet'!$B$14:$B$28,"Project",'Weekly Timesheet'!$D$14:$D$28,N34)),"") | W34: =IFERROR(IF(N34="","",SUMIFS('Weekly Timesheet'!$M$14:$M$28,'Weekly Timesheet'!$B$14:$B$28,"Project",'Weekly Timesheet'!$D$14:$D$28,N34)),"")
D35: Sick Time | H35: =IFERROR(SUMIFS('Weekly Timesheet'!$M$14:$M$28,'Weekly Timesheet'!$B$14:$B$28,"Admin",'Weekly Timesheet'!$C$14:$C$28,"Sick Time"),0) -> 0 | K35: =IFERROR(H35/SUMIF('Weekly Timesheet'!$B$14:$B$28,"Admin",'Weekly Timesheet'!$M$14:$M$28),0) -> 0 | N35: {=IFERROR(INDEX(_xlfn._xlws.SORT(_xlfn.UNIQUE(_xlfn._xlws.FILTER('Weekly Timesheet'!$D$14:$D$28,'Weekly Timesheet'!$B$14:$B$28="Project"))),12,1),"")} | P35: {=IFERROR(IF(N35="","",INDEX('Weekly Timesheet'!$C$14:$C$28,MATCH(1,('Weekly Timesheet'!$B$14:$B$28="Project")*('Weekly Timesheet'!$D$14:$D$28=N35),0))),"")} | Q35: =IFERROR(IF(N35="","",SUMIFS('Weekly Timesheet'!$E$14:$E$28,'Weekly Timesheet'!$B$14:$B$28,"Project",'Weekly Timesheet'!$D$14:$D$28,N35)),"") | R35: =IFERROR(IF(N35="","",SUMIFS('Weekly Timesheet'!$F$14:$F$28,'Weekly Timesheet'!$B$14:$B$28,"Project",'Weekly Timesheet'!$D$14:$D$28,N35)),"") | S35: =IFERROR(IF(N35="","",SUMIFS('Weekly Timesheet'!$G$14:$G$28,'Weekly Timesheet'!$B$14:$B$28,"Project",'Weekly Timesheet'!$D$14:$D$28,N35)),"") | T35: =IFERROR(IF(N35="","",SUMIFS('Weekly Timesheet'!$H$14:$H$28,'Weekly Timesheet'!$B$14:$B$28,"Project",'Weekly Timesheet'!$D$14:$D$28,N35)),"") | U35: =IFERROR(IF(N35="","",SUMIFS('Weekly Timesheet'!$I$14:$I$28,'Weekly Timesheet'!$B$14:$B$28,"Project",'Weekly Timesheet'!$D$14:$D$28,N35)),"") | V35: =IFERROR(IF(N35="","",SUMIFS('Weekly Timesheet'!$J$14:$J$28,'Weekly Timesheet'!$B$14:$B$28,"Project",'Weekly Timesheet'!$D$14:$D$28,N35)),"") | W35: =IFERROR(IF(N35="","",SUMIFS('Weekly Timesheet'!$M$14:$M$28,'Weekly Timesheet'!$B$14:$B$28,"Project",'Weekly Timesheet'!$D$14:$D$28,N35)),"")
D36: Vacation Hours | H36: =IFERROR(SUMIFS('Weekly Timesheet'!$M$14:$M$28,'Weekly Timesheet'!$B$14:$B$28,"Admin",'Weekly Timesheet'!$C$14:$C$28,"Vacation Hours"),0) -> 0 | K36: =IFERROR(H36/SUMIF('Weekly Timesheet'!$B$14:$B$28,"Admin",'Weekly Timesheet'!$M$14:$M$28),0) -> 0 | N36: {=IFERROR(INDEX(_xlfn._xlws.SORT(_xlfn.UNIQUE(_xlfn._xlws.FILTER('Weekly Timesheet'!$D$14:$D$28,'Weekly Timesheet'!$B$14:$B$28="Project"))),13,1),"")} | P36: {=IFERROR(IF(N36="","",INDEX('Weekly Timesheet'!$C$14:$C$28,MATCH(1,('Weekly Timesheet'!$B$14:$B$28="Project")*('Weekly Timesheet'!$D$14:$D$28=N36),0))),"")} | Q36: =IFERROR(IF(N36="","",SUMIFS('Weekly Timesheet'!$E$14:$E$28,'Weekly Timesheet'!$B$14:$B$28,"Project",'Weekly Timesheet'!$D$14:$D$28,N36)),"") | R36: =IFERROR(IF(N36="","",SUMIFS('Weekly Timesheet'!$F$14:$F$28,'Weekly Timesheet'!$B$14:$B$28,"Project",'Weekly Timesheet'!$D$14:$D$28,N36)),"") | S36: =IFERROR(IF(N36="","",SUMIFS('Weekly Timesheet'!$G$14:$G$28,'Weekly Timesheet'!$B$14:$B$28,"Project",'Weekly Timesheet'!$D$14:$D$28,N36)),"") | T36: =IFERROR(IF(N36="","",SUMIFS('Weekly Timesheet'!$H$14:$H$28,'Weekly Timesheet'!$B$14:$B$28,"Project",'Weekly Timesheet'!$D$14:$D$28,N36)),"") | U36: =IFERROR(IF(N36="","",SUMIFS('Weekly Timesheet'!$I$14:$I$28,'Weekly Timesheet'!$B$14:$B$28,"Project",'Weekly Timesheet'!$D$14:$D$28,N36)),"") | V36: =IFERROR(IF(N36="","",SUMIFS('Weekly Timesheet'!$J$14:$J$28,'Weekly Timesheet'!$B$14:$B$28,"Project",'Weekly Timesheet'!$D$14:$D$28,N36)),"") | W36: =IFERROR(IF(N36="","",SUMIFS('Weekly Timesheet'!$M$14:$M$28,'Weekly Timesheet'!$B$14:$B$28,"Project",'Weekly Timesheet'!$D$14:$D$28,N36)),"")
D37: Statutory Holiday | H37: =IFERROR(SUMIFS('Weekly Timesheet'!$M$14:$M$28,'Weekly Timesheet'!$B$14:$B$28,"Admin",'Weekly Timesheet'!$C$14:$C$28,"Statutory Holiday"),0) -> 8 | K37: =IFERROR(H37/SUMIF('Weekly Timesheet'!$B$14:$B$28,"Admin",'Weekly Timesheet'!$M$14:$M$28),0) -> 0.27586207 | N37: {=IFERROR(INDEX(_xlfn._xlws.SORT(_xlfn.UNIQUE(_xlfn._xlws.FILTER('Weekly Timesheet'!$D$14:$D$28,'Weekly Timesheet'!$B$14:$B$28="Project"))),14,1),"")} | P37: {=IFERROR(IF(N37="","",INDEX('Weekly Timesheet'!$C$14:$C$28,MATCH(1,('Weekly Timesheet'!$B$14:$B$28="Project")*('Weekly Timesheet'!$D$14:$D$28=N37),0))),"")} | Q37: =IFERROR(IF(N37="","",SUMIFS('Weekly Timesheet'!$E$14:$E$28,'Weekly Timesheet'!$B$14:$B$28,"Project",'Weekly Timesheet'!$D$14:$D$28,N37)),"") | R37: =IFERROR(IF(N37="","",SUMIFS('Weekly Timesheet'!$F$14:$F$28,'Weekly Timesheet'!$B$14:$B$28,"Project",'Weekly Timesheet'!$D$14:$D$28,N37)),"") | S37: =IFERROR(IF(N37="","",SUMIFS('Weekly Timesheet'!$G$14:$G$28,'Weekly Timesheet'!$B$14:$B$28,"Project",'Weekly Timesheet'!$D$14:$D$28,N37)),"") | T37: =IFERROR(IF(N37="","",SUMIFS('Weekly Timesheet'!$H$14:$H$28,'Weekly Timesheet'!$B$14:$B$28,"Project",'Weekly Timesheet'!$D$14:$D$28,N37)),"") | U37: =IFERROR(IF(N37="","",SUMIFS('Weekly Timesheet'!$I$14:$I$28,'Weekly Timesheet'!$B$14:$B$28,"Project",'Weekly Timesheet'!$D$14:$D$28,N37)),"") | V37: =IFERROR(IF(N37="","",SUMIFS('Weekly Timesheet'!$J$14:$J$28,'Weekly Timesheet'!$B$14:$B$28,"Project",'Weekly Timesheet'!$D$14:$D$28,N37)),"") | W37: =IFERROR(IF(N37="","",SUMIFS('Weekly Timesheet'!$M$14:$M$28,'Weekly Timesheet'!$B$14:$B$28,"Project",'Weekly Timesheet'!$D$14:$D$28,N37)),"")
D38: Administrative | H38: =IFERROR(SUMIFS('Weekly Timesheet'!$M$14:$M$28,'Weekly Timesheet'!$B$14:$B$28,"Admin",'Weekly Timesheet'!$C$14:$C$28,"Administrative"),0) -> 0 | K38: =IFERROR(H38/SUMIF('Weekly Timesheet'!$B$14:$B$28,"Admin",'Weekly Timesheet'!$M$14:$M$28),0) -> 0 | N38: {=IFERROR(INDEX(_xlfn._xlws.SORT(_xlfn.UNIQUE(_xlfn._xlws.FILTER('Weekly Timesheet'!$D$14:$D$28,'Weekly Timesheet'!$B$14:$B$28="Project"))),15,1),"")} | P38: {=IFERROR(IF(N38="","",INDEX('Weekly Timesheet'!$C$14:$C$28,MATCH(1,('Weekly Timesheet'!$B$14:$B$28="Project")*('Weekly Timesheet'!$D$14:$D$28=N38),0))),"")} | Q38: =IFERROR(IF(N38="","",SUMIFS('Weekly Timesheet'!$E$14:$E$28,'Weekly Timesheet'!$B$14:$B$28,"Project",'Weekly Timesheet'!$D$14:$D$28,N38)),"") | R38: =IFERROR(IF(N38="","",SUMIFS('Weekly Timesheet'!$F$14:$F$28,'Weekly Timesheet'!$B$14:$B$28,"Project",'Weekly Timesheet'!$D$14:$D$28,N38)),"") | S38: =IFERROR(IF(N38="","",SUMIFS('Weekly Timesheet'!$G$14:$G$28,'Weekly Timesheet'!$B$14:$B$28,"Project",'Weekly Timesheet'!$D$14:$D$28,N38)),"") | T38: =IFERROR(IF(N38="","",SUMIFS('Weekly Timesheet'!$H$14:$H$28,'Weekly Timesheet'!$B$14:$B$28,"Project",'Weekly Timesheet'!$D$14:$D$28,N38)),"") | U38: =IFERROR(IF(N38="","",SUMIFS('Weekly Timesheet'!$I$14:$I$28,'Weekly Timesheet'!$B$14:$B$28,"Project",'Weekly Timesheet'!$D$14:$D$28,N38)),"") | V38: =IFERROR(IF(N38="","",SUMIFS('Weekly Timesheet'!$J$14:$J$28,'Weekly Timesheet'!$B$14:$B$28,"Project",'Weekly Timesheet'!$D$14:$D$28,N38)),"") | W38: =IFERROR(IF(N38="","",SUMIFS('Weekly Timesheet'!$M$14:$M$28,'Weekly Timesheet'!$B$14:$B$28,"Project",'Weekly Timesheet'!$D$14:$D$28,N38)),"")
D39: Toolbox Meeting | H39: =IFERROR(SUMIFS('Weekly Timesheet'!$M$14:$M$28,'Weekly Timesheet'!$B$14:$B$28,"Admin",'Weekly Timesheet'!$C$14:$C$28,"Toolbox Meeting"),0) -> 1 | K39: =IFERROR(H39/SUMIF('Weekly Timesheet'!$B$14:$B$28,"Admin",'Weekly Timesheet'!$M$14:$M$28),0) -> 0.034482759 | N39: TOTAL PROJECT HOURS | Q39: =IFERROR(SUMIF('Weekly Timesheet'!$B$14:$B$28,"Project",'Weekly Timesheet'!$E$14:$E$28),0) -> 8 | R39: =IFERROR(SUMIF('Weekly Timesheet'!$B$14:$B$28,"Project",'Weekly Timesheet'!$F$14:$F$28),0) -> 0 | S39: =IFERROR(SUMIF('Weekly Timesheet'!$B$14:$B$28,"Project",'Weekly Timesheet'!$G$14:$G$28),0) -> 0 | T39: =IFERROR(SUMIF('Weekly Timesheet'!$B$14:$B$28,"Project",'Weekly Timesheet'!$H$14:$H$28),0) -> 2 | U39: =IFERROR(SUMIF('Weekly Timesheet'!$B$14:$B$28,"Project",'Weekly Timesheet'!$I$14:$I$28),0) -> 0 | V39: =IFERROR(SUMIF('Weekly Timesheet'!$B$14:$B$28,"Project",'Weekly Timesheet'!$J$14:$J$28),0) -> 0 | W39: =IFERROR(SUMIF('Weekly Timesheet'!$B$14:$B$28,"Project",'Weekly Timesheet'!$M$14:$M$28),0) -> 10
B40: Office & Sales | D40: Customer Contact | H40: =IFERROR(SUMIFS('Weekly Timesheet'!$M$14:$M$28,'Weekly Timesheet'!$B$14:$B$28,"Office & Sales",'Weekly Timesheet'!$C$14:$C$28,"Customer Contact"),0) -> 0 | K40: =IFERROR(H40/SUMIF('Weekly Timesheet'!$B$14:$B$28,"Office & Sales",'Weekly Timesheet'!$M$14:$M$28),0) -> 0
D41: Project Development | H41: =IFERROR(SUMIFS('Weekly Timesheet'!$M$14:$M$28,'Weekly Timesheet'!$B$14:$B$28,"Office & Sales",'Weekly Timesheet'!$C$14:$C$28,"Project Development"),0) -> 0 | K41: =IFERROR(H41/SUMIF('Weekly Timesheet'!$B$14:$B$28,"Office & Sales",'Weekly Timesheet'!$M$14:$M$28),0) -> 0
D42: Proposals & Quotes | H42: =IFERROR(SUMIFS('Weekly Timesheet'!$M$14:$M$28,'Weekly Timesheet'!$B$14:$B$28,"Office & Sales",'Weekly Timesheet'!$C$14:$C$28,"Proposals & Quotes"),0) -> 0 | K42: =IFERROR(H42/SUMIF('Weekly Timesheet'!$B$14:$B$28,"Office & Sales",'Weekly Timesheet'!$M$14:$M$28),0) -> 0
D43: Inventory | H43: =IFERROR(SUMIFS('Weekly Timesheet'!$M$14:$M$28,'Weekly Timesheet'!$B$14:$B$28,"Office & Sales",'Weekly Timesheet'!$C$14:$C$28,"Inventory"),0) -> 0 | K43: =IFERROR(H43/SUMIF('Weekly Timesheet'!$B$14:$B$28,"Office & Sales",'Weekly Timesheet'!$M$14:$M$28),0) -> 0
D44: SRU Study | H44: =IFERROR(SUMIFS('Weekly Timesheet'!$M$14:$M$28,'Weekly Timesheet'!$B$14:$B$28,"Office & Sales",'Weekly Timesheet'!$C$14:$C$28,"SRU Study"),0) -> 0 | K44: =IFERROR(H44/SUMIF('Weekly Timesheet'!$B$14:$B$28,"Office & Sales",'Weekly Timesheet'!$M$14:$M$28),0) -> 0
D45: Conference | H45: =IFERROR(SUMIFS('Weekly Timesheet'!$M$14:$M$28,'Weekly Timesheet'!$B$14:$B$28,"Office & Sales",'Weekly Timesheet'!$C$14:$C$28,"Conference"),0) -> 0 | K45: =IFERROR(H45/SUMIF('Weekly Timesheet'!$B$14:$B$28,"Office & Sales",'Weekly Timesheet'!$M$14:$M$28),0) -> 0
D46: General | H46: =IFERROR(SUMIFS('Weekly Timesheet'!$M$14:$M$28,'Weekly Timesheet'!$B$14:$B$28,"Office & Sales",'Weekly Timesheet'!$C$14:$C$28,"General"),0) -> 21 | K46: =IFERROR(H46/SUMIF('Weekly Timesheet'!$B$14:$B$28,"Office & Sales",'Weekly Timesheet'!$M$14:$M$28),0) -> 1
B48: TIMESHEET ENTRY LOG
B50: # | C50: Main Category | D50: Sub-Category | E50: Project No. | F50: Mon | G50: Tue | H50: Wed | I50: Thu | J50: Fri | K50: Sat | L50: Sun | M50: Task Description | W50: Total hrs
B51: =IFERROR(IF('Weekly Timesheet'!B14="","",1),"") -> 1 | C51: =IFERROR(IF('Weekly Timesheet'!B14="","",'Weekly Timesheet'!B14),"") -> Admin | D51: =IFERROR(IF('Weekly Timesheet'!C14="","",'Weekly Timesheet'!C14),"") -> TIL Payout | E51: =IFERROR(IF('Weekly Timesheet'!D14="","",'Weekly Timesheet'!D14),"") | F51: =IFERROR(IF('Weekly Timesheet'!B14="","",'Weekly Timesheet'!E14),"") -> 0 | G51: =IFERROR(IF('Weekly Timesheet'!B14="","",'Weekly Timesheet'!F14),"") -> 20 | H51: =IFERROR(IF('Weekly Timesheet'!B14="","",'Weekly Timesheet'!G14),"") -> 0 | I51: =IFERROR(IF('Weekly Timesheet'!B14="","",'Weekly Timesheet'!H14),"") -> 0 | J51: =IFERROR(IF('Weekly Timesheet'!B14="","",'Weekly Timesheet'!I14),"") -> 0 | K51: =IFERROR(IF('Weekly Timesheet'!B14="","",'Weekly Timesheet'!J14),"") -> 0 | L51: =IFERROR(IF('Weekly Timesheet'!B14="","",'Weekly Timesheet'!K14),"") -> 0 | M51: =IFERROR(IF('Weekly Timesheet'!L14="","",'Weekly Timesheet'!L14),"") -> Recived Payment | W51: =IFERROR(IF('Weekly Timesheet'!B14="","",'Weekly Timesheet'!M14),"") -> 20
B52: =IFERROR(IF('Weekly Timesheet'!B15="","",2),"") -> 2 | C52: =IFERROR(IF('Weekly Timesheet'!B15="","",'Weekly Timesheet'!B15),"") -> Project | D52: =IFERROR(IF('Weekly Timesheet'!C15="","",'Weekly Timesheet'!C15),"") -> Site Travel | E52: =IFERROR(IF('Weekly Timesheet'!D15="","",'Weekly Timesheet'!D15),"") -> 2026125 | F52: =IFERROR(IF('Weekly Timesheet'!B15="","",'Weekly Timesheet'!E15),"") -> 8 | G52: =IFERROR(IF('Weekly Timesheet'!B15="","",'Weekly Timesheet'!F15),"") -> 0 | H52: =IFERROR(IF('Weekly Timesheet'!B15="","",'Weekly Timesheet'!G15),"") -> 0 | I52: =IFERROR(IF('Weekly Timesheet'!B15="","",'Weekly Timesheet'!H15),"") -> 0 | J52: =IFERROR(IF('Weekly Timesheet'!B15="","",'Weekly Timesheet'!I15),"") -> 0 | K52: =IFERROR(IF('Weekly Timesheet'!B15="","",'Weekly Timesheet'!J15),"") -> 0 | L52: =IFERROR(IF('Weekly Timesheet'!B15="","",'Weekly Timesheet'!K15),"") -> 0 | M52: =IFERROR(IF('Weekly Timesheet'!L15="","",'Weekly Timesheet'!L15),"") -> Travel to YYC | W52: =IFERROR(IF('Weekly Timesheet'!B15="","",'Weekly Timesheet'!M15),"") -> 8
B53: =IFERROR(IF('Weekly Timesheet'!B16="","",3),"") -> 3 | C53: =IFERROR(IF('Weekly Timesheet'!B16="","",'Weekly Timesheet'!B16),"") -> Admin | D53: =IFERROR(IF('Weekly Timesheet'!C16="","",'Weekly Timesheet'!C16),"") -> Toolbox Meeting | E53: =IFERROR(IF('Weekly Timesheet'!D16="","",'Weekly Timesheet'!D16),"") | F53: =IFERROR(IF('Weekly Timesheet'!B16="","",'Weekly Timesheet'!E16),"") -> 0 | G53: =IFERROR(IF('Weekly Timesheet'!B16="","",'Weekly Timesheet'!F16),"") -> 0 | H53: =IFERROR(IF('Weekly Timesheet'!B16="","",'Weekly Timesheet'!G16),"") -> 1 | I53: =IFERROR(IF('Weekly Timesheet'!B16="","",'Weekly Timesheet'!H16),"") -> 0 | J53: =IFERROR(IF('Weekly Timesheet'!B16="","",'Weekly Timesheet'!I16),"") -> 0 | K53: =IFERROR(IF('Weekly Timesheet'!B16="","",'Weekly Timesheet'!J16),"") -> 0 | L53: =IFERROR(IF('Weekly Timesheet'!B16="","",'Weekly Timesheet'!K16),"") -> 0 | M53: =IFERROR(IF('Weekly Timesheet'!L16="","",'Weekly Timesheet'!L16),"") -> Pit Stop | W53: =IFERROR(IF('Weekly Timesheet'!B16="","",'Weekly Timesheet'!M16),"") -> 1
B54: =IFERROR(IF('Weekly Timesheet'!B17="","",4),"") -> 4 | C54: =IFERROR(IF('Weekly Timesheet'!B17="","",'Weekly Timesheet'!B17),"") -> Office & Sales | D54: =IFERROR(IF('Weekly Timesheet'!C17="","",'Weekly Timesheet'!C17),"") -> General | E54: =IFERROR(IF('Weekly Timesheet'!D17="","",'Weekly Timesheet'!D17),"") | F54: =IFERROR(IF('Weekly Timesheet'!B17="","",'Weekly Timesheet'!E17),"") -> 0 | G54: =IFERROR(IF('Weekly Timesheet'!B17="","",'Weekly Timesheet'!F17),"") -> 8 | H54: =IFERROR(IF('Weekly Timesheet'!B17="","",'Weekly Timesheet'!G17),"") -> 7 | I54: =IFERROR(IF('Weekly Timesheet'!B17="","",'Weekly Timesheet'!H17),"") -> 6 | J54: =IFERROR(IF('Weekly Timesheet'!B17="","",'Weekly Timesheet'!I17),"") -> 0 | K54: =IFERROR(IF('Weekly Timesheet'!B17="","",'Weekly Timesheet'!J17),"") -> 0 | L54: =IFERROR(IF('Weekly Timesheet'!B17="","",'Weekly Timesheet'!K17),"") -> 0 | M54: =IFERROR(IF('Weekly Timesheet'!L17="","",'Weekly Timesheet'!L17),"") -> Timesheet; Email Reply; Timesheet and Expense report template for Team | W54: =IFERROR(IF('Weekly Timesheet'!B17="","",'Weekly Timesheet'!M17),"") -> 21
B55: =IFERROR(IF('Weekly Timesheet'!B18="","",5),"") -> 5 | C55: =IFERROR(IF('Weekly Timesheet'!B18="","",'Weekly Timesheet'!B18),"") -> Project | D55: =IFERROR(IF('Weekly Timesheet'!C18="","",'Weekly Timesheet'!C18),"") -> Report | E55: =IFERROR(IF('Weekly Timesheet'!D18="","",'Weekly Timesheet'!D18),"") -> 2026125 | F55: =IFERROR(IF('Weekly Timesheet'!B18="","",'Weekly Timesheet'!E18),"") -> 0 | G55: =IFERROR(IF('Weekly Timesheet'!B18="","",'Weekly Timesheet'!F18),"") -> 0 | H55: =IFERROR(IF('Weekly Timesheet'!B18="","",'Weekly Timesheet'!G18),"") -> 0 | I55: =IFERROR(IF('Weekly Timesheet'!B18="","",'Weekly Timesheet'!H18),"") -> 2 | J55: =IFERROR(IF('Weekly Timesheet'!B18="","",'Weekly Timesheet'!I18),"") -> 0 | K55: =IFERROR(IF('Weekly Timesheet'!B18="","",'Weekly Timesheet'!J18),"") -> 0 | L55: =IFERROR(IF('Weekly Timesheet'!B18="","",'Weekly Timesheet'!K18),"") -> 0 | M55: =IFERROR(IF('Weekly Timesheet'!L18="","",'Weekly Timesheet'!L18),"") -> Summary Letter | W55: =IFERROR(IF('Weekly Timesheet'!B18="","",'Weekly Timesheet'!M18),"") -> 2
B56: =IFERROR(IF('Weekly Timesheet'!B19="","",6),"") -> 6 | C56: =IFERROR(IF('Weekly Timesheet'!B19="","",'Weekly Timesheet'!B19),"") -> Admin | D56: =IFERROR(IF('Weekly Timesheet'!C19="","",'Weekly Timesheet'!C19),"") -> Statutory Holiday | E56: =IFERROR(IF('Weekly Timesheet'!D19="","",'Weekly Timesheet'!D19),"") | F56: =IFERROR(IF('Weekly Timesheet'!B19="","",'Weekly Timesheet'!E19),"") -> 0 | G56: =IFERROR(IF('Weekly Timesheet'!B19="","",'Weekly Timesheet'!F19),"") -> 0 | H56: =IFERROR(IF('Weekly Timesheet'!B19="","",'Weekly Timesheet'!G19),"") -> 0 | I56: =IFERROR(IF('Weekly Timesheet'!B19="","",'Weekly Timesheet'!H19),"") -> 0 | J56: =IFERROR(IF('Weekly Timesheet'!B19="","",'Weekly Timesheet'!I19),"") -> 8 | K56: =IFERROR(IF('Weekly Timesheet'!B19="","",'Weekly Timesheet'!J19),"") -> 0 | L56: =IFERROR(IF('Weekly Timesheet'!B19="","",'Weekly Timesheet'!K19),"") -> 0 | M56: =IFERROR(IF('Weekly Timesheet'!L19="","",'Weekly Timesheet'!L19),"") -> Good Friday | W56: =IFERROR(IF('Weekly Timesheet'!B19="","",'Weekly Timesheet'!M19),"") -> 8
B57: =IFERROR(IF('Weekly Timesheet'!B20="","",7),"") | C57: =IFERROR(IF('Weekly Timesheet'!B20="","",'Weekly Timesheet'!B20),"") | D57: =IFERROR(IF('Weekly Timesheet'!C20="","",'Weekly Timesheet'!C20),"") | E57: =IFERROR(IF('Weekly Timesheet'!D20="","",'Weekly Timesheet'!D20),"") | F57: =IFERROR(IF('Weekly Timesheet'!B20="","",'Weekly Timesheet'!E20),"") | G57: =IFERROR(IF('Weekly Timesheet'!B20="","",'Weekly Timesheet'!F20),"") | H57: =IFERROR(IF('Weekly Timesheet'!B20="","",'Weekly Timesheet'!G20),"") | I57: =IFERROR(IF('Weekly Timesheet'!B20="","",'Weekly Timesheet'!H20),"") | J57: =IFERROR(IF('Weekly Timesheet'!B20="","",'Weekly Timesheet'!I20),"") | K57: =IFERROR(IF('Weekly Timesheet'!B20="","",'Weekly Timesheet'!J20),"") | L57: =IFERROR(IF('Weekly Timesheet'!B20="","",'Weekly Timesheet'!K20),"") | M57: =IFERROR(IF('Weekly Timesheet'!L20="","",'Weekly Timesheet'!L20),"") | W57: =IFERROR(IF('Weekly Timesheet'!B20="","",'Weekly Timesheet'!M20),"")
B58: =IFERROR(IF('Weekly Timesheet'!B21="","",8),"") | C58: =IFERROR(IF('Weekly Timesheet'!B21="","",'Weekly Timesheet'!B21),"") | D58: =IFERROR(IF('Weekly Timesheet'!C21="","",'Weekly Timesheet'!C21),"") | E58: =IFERROR(IF('Weekly Timesheet'!D21="","",'Weekly Timesheet'!D21),"") | F58: =IFERROR(IF('Weekly Timesheet'!B21="","",'Weekly Timesheet'!E21),"") | G58: =IFERROR(IF('Weekly Timesheet'!B21="","",'Weekly Timesheet'!F21),"") | H58: =IFERROR(IF('Weekly Timesheet'!B21="","",'Weekly Timesheet'!G21),"") | I58: =IFERROR(IF('Weekly Timesheet'!B21="","",'Weekly Timesheet'!H21),"") | J58: =IFERROR(IF('Weekly Timesheet'!B21="","",'Weekly Timesheet'!I21),"") | K58: =IFERROR(IF('Weekly Timesheet'!B21="","",'Weekly Timesheet'!J21),"") | L58: =IFERROR(IF('Weekly Timesheet'!B21="","",'Weekly Timesheet'!K21),"") | M58: =IFERROR(IF('Weekly Timesheet'!L21="","",'Weekly Timesheet'!L21),"") | W58: =IFERROR(IF('Weekly Timesheet'!B21="","",'Weekly Timesheet'!M21),"")
B59: =IFERROR(IF('Weekly Timesheet'!B22="","",9),"") | C59: =IFERROR(IF('Weekly Timesheet'!B22="","",'Weekly Timesheet'!B22),"") | D59: =IFERROR(IF('Weekly Timesheet'!C22="","",'Weekly Timesheet'!C22),"") | E59: =IFERROR(IF('Weekly Timesheet'!D22="","",'Weekly Timesheet'!D22),"") | F59: =IFERROR(IF('Weekly Timesheet'!B22="","",'Weekly Timesheet'!E22),"") | G59: =IFERROR(IF('Weekly Timesheet'!B22="","",'Weekly Timesheet'!F22),"") | H59: =IFERROR(IF('Weekly Timesheet'!B22="","",'Weekly Timesheet'!G22),"") | I59: =IFERROR(IF('Weekly Timesheet'!B22="","",'Weekly Timesheet'!H22),"") | J59: =IFERROR(IF('Weekly Timesheet'!B22="","",'Weekly Timesheet'!I22),"") | K59: =IFERROR(IF('Weekly Timesheet'!B22="","",'Weekly Timesheet'!J22),"") | L59: =IFERROR(IF('Weekly Timesheet'!B22="","",'Weekly Timesheet'!K22),"") | M59: =IFERROR(IF('Weekly Timesheet'!L22="","",'Weekly Timesheet'!L22),"") | W59: =IFERROR(IF('Weekly Timesheet'!B22="","",'Weekly Timesheet'!M22),"")
B60: =IFERROR(IF('Weekly Timesheet'!B23="","",10),"") | C60: =IFERROR(IF('Weekly Timesheet'!B23="","",'Weekly Timesheet'!B23),"") | D60: =IFERROR(IF('Weekly Timesheet'!C23="","",'Weekly Timesheet'!C23),"") | E60: =IFERROR(IF('Weekly Timesheet'!D23="","",'Weekly Timesheet'!D23),"") | F60: =IFERROR(IF('Weekly Timesheet'!B23="","",'Weekly Timesheet'!E23),"") | G60: =IFERROR(IF('Weekly Timesheet'!B23="","",'Weekly Timesheet'!F23),"") | H60: =IFERROR(IF('Weekly Timesheet'!B23="","",'Weekly Timesheet'!G23),"") | I60: =IFERROR(IF('Weekly Timesheet'!B23="","",'Weekly Timesheet'!H23),"") | J60: =IFERROR(IF('Weekly Timesheet'!B23="","",'Weekly Timesheet'!I23),"") | K60: =IFERROR(IF('Weekly Timesheet'!B23="","",'Weekly Timesheet'!J23),"") | L60: =IFERROR(IF('Weekly Timesheet'!B23="","",'Weekly Timesheet'!K23),"") | M60: =IFERROR(IF('Weekly Timesheet'!L23="","",'Weekly Timesheet'!L23),"") | W60: =IFERROR(IF('Weekly Timesheet'!B23="","",'Weekly Timesheet'!M23),"")
B61: =IFERROR(IF('Weekly Timesheet'!B24="","",11),"") | C61: =IFERROR(IF('Weekly Timesheet'!B24="","",'Weekly Timesheet'!B24),"") | D61: =IFERROR(IF('Weekly Timesheet'!C24="","",'Weekly Timesheet'!C24),"") | E61: =IFERROR(IF('Weekly Timesheet'!D24="","",'Weekly Timesheet'!D24),"") | F61: =IFERROR(IF('Weekly Timesheet'!B24="","",'Weekly Timesheet'!E24),"") | G61: =IFERROR(IF('Weekly Timesheet'!B24="","",'Weekly Timesheet'!F24),"") | H61: =IFERROR(IF('Weekly Timesheet'!B24="","",'Weekly Timesheet'!G24),"") | I61: =IFERROR(IF('Weekly Timesheet'!B24="","",'Weekly Timesheet'!H24),"") | J61: =IFERROR(IF('Weekly Timesheet'!B24="","",'Weekly Timesheet'!I24),"") | K61: =IFERROR(IF('Weekly Timesheet'!B24="","",'Weekly Timesheet'!J24),"") | L61: =IFERROR(IF('Weekly Timesheet'!B24="","",'Weekly Timesheet'!K24),"") | M61: =IFERROR(IF('Weekly Timesheet'!L24="","",'Weekly Timesheet'!L24),"") | W61: =IFERROR(IF('Weekly Timesheet'!B24="","",'Weekly Timesheet'!M24),"")
B62: =IFERROR(IF('Weekly Timesheet'!B25="","",12),"") | C62: =IFERROR(IF('Weekly Timesheet'!B25="","",'Weekly Timesheet'!B25),"") | D62: =IFERROR(IF('Weekly Timesheet'!C25="","",'Weekly Timesheet'!C25),"") | E62: =IFERROR(IF('Weekly Timesheet'!D25="","",'Weekly Timesheet'!D25),"") | F62: =IFERROR(IF('Weekly Timesheet'!B25="","",'Weekly Timesheet'!E25),"") | G62: =IFERROR(IF('Weekly Timesheet'!B25="","",'Weekly Timesheet'!F25),"") | H62: =IFERROR(IF('Weekly Timesheet'!B25="","",'Weekly Timesheet'!G25),"") | I62: =IFERROR(IF('Weekly Timesheet'!B25="","",'Weekly Timesheet'!H25),"") | J62: =IFERROR(IF('Weekly Timesheet'!B25="","",'Weekly Timesheet'!I25),"") | K62: =IFERROR(IF('Weekly Timesheet'!B25="","",'Weekly Timesheet'!J25),"") | L62: =IFERROR(IF('Weekly Timesheet'!B25="","",'Weekly Timesheet'!K25),"") | M62: =IFERROR(IF('Weekly Timesheet'!L25="","",'Weekly Timesheet'!L25),"") | W62: =IFERROR(IF('Weekly Timesheet'!B25="","",'Weekly Timesheet'!M25),"")
B63: =IFERROR(IF('Weekly Timesheet'!B26="","",13),"") | C63: =IFERROR(IF('Weekly Timesheet'!B26="","",'Weekly Timesheet'!B26),"") | D63: =IFERROR(IF('Weekly Timesheet'!C26="","",'Weekly Timesheet'!C26),"") | E63: =IFERROR(IF('Weekly Timesheet'!D26="","",'Weekly Timesheet'!D26),"") | F63: =IFERROR(IF('Weekly Timesheet'!B26="","",'Weekly Timesheet'!E26),"") | G63: =IFERROR(IF('Weekly Timesheet'!B26="","",'Weekly Timesheet'!F26),"") | H63: =IFERROR(IF('Weekly Timesheet'!B26="","",'Weekly Timesheet'!G26),"") | I63: =IFERROR(IF('Weekly Timesheet'!B26="","",'Weekly Timesheet'!H26),"") | J63: =IFERROR(IF('Weekly Timesheet'!B26="","",'Weekly Timesheet'!I26),"") | K63: =IFERROR(IF('Weekly Timesheet'!B26="","",'Weekly Timesheet'!J26),"") | L63: =IFERROR(IF('Weekly Timesheet'!B26="","",'Weekly Timesheet'!K26),"") | M63: =IFERROR(IF('Weekly Timesheet'!L26="","",'Weekly Timesheet'!L26),"") | W63: =IFERROR(IF('Weekly Timesheet'!B26="","",'Weekly Timesheet'!M26),"")
B64: =IFERROR(IF('Weekly Timesheet'!B27="","",14),"") | C64: =IFERROR(IF('Weekly Timesheet'!B27="","",'Weekly Timesheet'!B27),"") | D64: =IFERROR(IF('Weekly Timesheet'!C27="","",'Weekly Timesheet'!C27),"") | E64: =IFERROR(IF('Weekly Timesheet'!D27="","",'Weekly Timesheet'!D27),"") | F64: =IFERROR(IF('Weekly Timesheet'!B27="","",'Weekly Timesheet'!E27),"") | G64: =IFERROR(IF('Weekly Timesheet'!B27="","",'Weekly Timesheet'!F27),"") | H64: =IFERROR(IF('Weekly Timesheet'!B27="","",'Weekly Timesheet'!G27),"") | I64: =IFERROR(IF('Weekly Timesheet'!B27="","",'Weekly Timesheet'!H27),"") | J64: =IFERROR(IF('Weekly Timesheet'!B27="","",'Weekly Timesheet'!I27),"") | K64: =IFERROR(IF('Weekly Timesheet'!B27="","",'Weekly Timesheet'!J27),"") | L64: =IFERROR(IF('Weekly Timesheet'!B27="","",'Weekly Timesheet'!K27),"") | M64: =IFERROR(IF('Weekly Timesheet'!L27="","",'Weekly Timesheet'!L27),"") | W64: =IFERROR(IF('Weekly Timesheet'!B27="","",'Weekly Timesheet'!M27),"")
B65: =IFERROR(IF('Weekly Timesheet'!B28="","",15),"") | C65: =IFERROR(IF('Weekly Timesheet'!B28="","",'Weekly Timesheet'!B28),"") | D65: =IFERROR(IF('Weekly Timesheet'!C28="","",'Weekly Timesheet'!C28),"") | E65: =IFERROR(IF('Weekly Timesheet'!D28="","",'Weekly Timesheet'!D28),"") | F65: =IFERROR(IF('Weekly Timesheet'!B28="","",'Weekly Timesheet'!E28),"") | G65: =IFERROR(IF('Weekly Timesheet'!B28="","",'Weekly Timesheet'!F28),"") | H65: =IFERROR(IF('Weekly Timesheet'!B28="","",'Weekly Timesheet'!G28),"") | I65: =IFERROR(IF('Weekly Timesheet'!B28="","",'Weekly Timesheet'!H28),"") | J65: =IFERROR(IF('Weekly Timesheet'!B28="","",'Weekly Timesheet'!I28),"") | K65: =IFERROR(IF('Weekly Timesheet'!B28="","",'Weekly Timesheet'!J28),"") | L65: =IFERROR(IF('Weekly Timesheet'!B28="","",'Weekly Timesheet'!K28),"") | M65: =IFERROR(IF('Weekly Timesheet'!L28="","",'Weekly Timesheet'!L28),"") | W65: =IFERROR(IF('Weekly Timesheet'!B28="","",'Weekly Timesheet'!M28),"")
B66: WEEK TOTALS | F66: =IFERROR(SUM('Weekly Timesheet'!E14:E28),0) -> 8 | G66: =IFERROR(SUM('Weekly Timesheet'!F14:F28),0) -> 28 | H66: =IFERROR(SUM('Weekly Timesheet'!G14:G28),0) -> 8 | I66: =IFERROR(SUM('Weekly Timesheet'!H14:H28),0) -> 8 | J66: =IFERROR(SUM('Weekly Timesheet'!I14:I28),0) -> 8 | K66: =IFERROR(SUM('Weekly Timesheet'!J14:J28),0) -> 0 | L66: =IFERROR(SUM('Weekly Timesheet'!K14:K28),0) -> 0 | W66: =IFERROR(SUM('Weekly Timesheet'!M14:M28),0) -> 60
B68: ⓘ All data pulls automatically from the Weekly Timesheet. Read-only — edit source data in the Weekly Timesheet tab only. Project breakdown shows each unique project number exactly once.

Sheet 📄 Weekly Report (Backup)
B2: 📄 WEEKLY TIMESHEET REPORT · Sulfur Recovery Engineering Inc.
B4: Employee Name | D4: ='Weekly Timesheet'!C4 -> Utsav Chovatia | H4: Week Starting | J4: ='Weekly Timesheet'!F4 -> 46111
B5: Employee ID | D5: ='Weekly Timesheet'!C5 -> 1 | H5: Status | J5: ='Weekly Timesheet'!F5 -> Submitted
B6: Department | D6: ='Weekly Timesheet'!C6 -> Engineering | H6: Approved By | J6: ='Weekly Timesheet'!F6 -> 0
B7: Report Generated | H7: =TEXT(TODAY(),"DD MMMM YYYY") -> 18 June 2026
B9: WEEK AT A GLANCE
B10: =IFERROR(SUM('Weekly Timesheet'!$M$14:$M$28),0) -> 60 | E10: ='Weekly Timesheet'!I9 -> 0 | H10: ='Weekly Timesheet'!M9 -> 823.25 | J10: ='Weekly Timesheet'!M10 -> 48 | L10: =IFERROR(SUMIF('Weekly Timesheet'!$B$14:$B$28,"Project",'Weekly Timesheet'!$M$14:$M$28),0) -> 10
B11: Total Hours Logged | E11: Overtime Earned | H11: TIL Bank Remaining | J11: Vacation Hrs Remaining | L11: Project Hours This Week
B13: DAILY HOURS BREAKDOWN
B15: Category | E15: Mon | F15: Tue | G15: Wed | H15: Thu | I15: Fri | J15: Sat | K15: Sun | L15: Week Total | M15: OT hrs
B16: Regular Hours | E16: =IFERROR(SUM('Weekly Timesheet'!E14:E28)-MAX(0,SUM('Weekly Timesheet'!E14:E28)-8),0) -> 8 | F16: =IFERROR(SUM('Weekly Timesheet'!F14:F28)-MAX(0,SUM('Weekly Timesheet'!F14:F28)-8),0) -> 8 | G16: =IFERROR(SUM('Weekly Timesheet'!G14:G28)-MAX(0,SUM('Weekly Timesheet'!G14:G28)-8),0) -> 8 | H16: =IFERROR(SUM('Weekly Timesheet'!H14:H28)-MAX(0,SUM('Weekly Timesheet'!H14:H28)-8),0) -> 8 | I16: =IFERROR(SUM('Weekly Timesheet'!I14:I28)-MAX(0,SUM('Weekly Timesheet'!I14:I28)-8),0) -> 8 | J16: 0 | K16: 0 | L16: =SUM(E16:K16) -> 40
B17: Overtime | E17: =IFERROR(MAX(0, SUMIFS('Weekly Timesheet'!E14:E28, 'Weekly Timesheet'!$C$14:$C$28, "<>TIL Payout") - 8), 0) -> 0 | F17: =IFERROR(MAX(0, SUMIFS('Weekly Timesheet'!F14:F28, 'Weekly Timesheet'!$C$14:$C$28, "<>TIL Payout") - 8), 0) -> 0 | G17: =IFERROR(MAX(0, SUMIFS('Weekly Timesheet'!G14:G28, 'Weekly Timesheet'!$C$14:$C$28, "<>TIL Payout") - 8), 0) -> 0 | H17: =IFERROR(MAX(0, SUMIFS('Weekly Timesheet'!H14:H28, 'Weekly Timesheet'!$C$14:$C$28, "<>TIL Payout") - 8), 0) -> 0 | I17: =IFERROR(MAX(0, SUMIFS('Weekly Timesheet'!I14:I28, 'Weekly Timesheet'!$C$14:$C$28, "<>TIL Payout") - 8), 0) -> 0 | J17: =SUM('Weekly Timesheet'!J14:J28) -> 0 | K17: =SUM('Weekly Timesheet'!K14:K28) -> 0 | L17: =SUM(E17:K17) -> 0 | M17: ='Weekly Timesheet'!I9 -> 0
B18: TIL Payout | E18: =IFERROR(SUMIFS('Weekly Timesheet'!E14:E28, 'Weekly Timesheet'!$C$14:$C$28, "TIL Payout"), 0) -> 0 | F18: =IFERROR(SUMIFS('Weekly Timesheet'!F14:F28, 'Weekly Timesheet'!$C$14:$C$28, "TIL Payout"), 0) -> 20 | G18: =IFERROR(SUMIFS('Weekly Timesheet'!G14:G28, 'Weekly Timesheet'!$C$14:$C$28, "TIL Payout"), 0) -> 0 | H18: =IFERROR(SUMIFS('Weekly Timesheet'!H14:H28, 'Weekly Timesheet'!$C$14:$C$28, "TIL Payout"), 0) -> 0 | I18: =IFERROR(SUMIFS('Weekly Timesheet'!I14:I28, 'Weekly Timesheet'!$C$14:$C$28, "TIL Payout"), 0) -> 0 | J18: =IFERROR(SUMIFS('Weekly Timesheet'!J14:J28, 'Weekly Timesheet'!$C$14:$C$28, "TIL Payout"), 0) -> 0 | K18: =IFERROR(SUMIFS('Weekly Timesheet'!K14:K28, 'Weekly Timesheet'!$C$14:$C$28, "TIL Payout"), 0) -> 0 | L18: =SUM(E18:K18) -> 20
B19: Total Hours | E19: =IFERROR(SUM('Weekly Timesheet'!E14:E28),0) -> 8 | F19: =IFERROR(SUM('Weekly Timesheet'!F14:F28),0) -> 28 | G19: =IFERROR(SUM('Weekly Timesheet'!G14:G28),0) -> 8 | H19: =IFERROR(SUM('Weekly Timesheet'!H14:H28),0) -> 8 | I19: =IFERROR(SUM('Weekly Timesheet'!I14:I28),0) -> 8 | J19: =IFERROR(SUM('Weekly Timesheet'!J14:J28),0) -> 0 | K19: =IFERROR(SUM('Weekly Timesheet'!K14:K28),0) -> 0 | L19: =SUM(E19:K19) -> 60
B21: HOURS BY CATEGORY
B23: Category | I23: Total Hours | L23: % of Week Total
B24: Project | I24: =IFERROR(SUMIF('Weekly Timesheet'!$B$14:$B$28,"Project",'Weekly Timesheet'!$M$14:$M$28),0) -> 10 | L24: =IFERROR(SUMIF('Weekly Timesheet'!$B$14:$B$28,"Project",'Weekly Timesheet'!$M$14:$M$28)/(IFERROR(SUM('Weekly Timesheet'!$M$14:$M$28),1)),0) -> 0.16666667
B25: Admin | I25: =IFERROR(SUMIF('Weekly Timesheet'!$B$14:$B$28,"Admin",'Weekly Timesheet'!$M$14:$M$28),0) -> 29 | L25: =IFERROR(SUMIF('Weekly Timesheet'!$B$14:$B$28,"Admin",'Weekly Timesheet'!$M$14:$M$28)/(IFERROR(SUM('Weekly Timesheet'!$M$14:$M$28),1)),0) -> 0.48333333
B26: Office & Sales | I26: =IFERROR(SUMIF('Weekly Timesheet'!$B$14:$B$28,"Office & Sales",'Weekly Timesheet'!$M$14:$M$28),0) -> 21 | L26: =IFERROR(SUMIF('Weekly Timesheet'!$B$14:$B$28,"Office & Sales",'Weekly Timesheet'!$M$14:$M$28)/(IFERROR(SUM('Weekly Timesheet'!$M$14:$M$28),1)),0) -> 0.35
B27: TOTAL | I27: =IFERROR(SUM('Weekly Timesheet'!$M$14:$M$28),0) -> 60 | L27: 100%
B29: HOURS BY SUB-CATEGORY
B31: Main Category | E31: Sub-Category | H31: Hours | K31: % of Category
B32: Project | E32: Travel | H32: =IFERROR(SUMIFS('Weekly Timesheet'!$M$14:$M$28,'Weekly Timesheet'!$C$14:$C$28,"Travel"),0) -> 0 | K32: =IFERROR(SUMIFS('Weekly Timesheet'!$M$14:$M$28,'Weekly Timesheet'!$C$14:$C$28,"Travel")/(IFERROR(SUMIF('Weekly Timesheet'!$B$14:$B$28,"Project",'Weekly Timesheet'!$M$14:$M$28),1)),0) -> 0
E33: Site Travel | H33: =IFERROR(SUMIFS('Weekly Timesheet'!$M$14:$M$28,'Weekly Timesheet'!$C$14:$C$28,"Site Travel"),0) -> 8 | K33: =IFERROR(SUMIFS('Weekly Timesheet'!$M$14:$M$28,'Weekly Timesheet'!$C$14:$C$28,"Site Travel")/(IFERROR(SUMIF('Weekly Timesheet'!$B$14:$B$28,"Project",'Weekly Timesheet'!$M$14:$M$28),1)),0) -> 0.8
E34: Site Work | H34: =IFERROR(SUMIFS('Weekly Timesheet'!$M$14:$M$28,'Weekly Timesheet'!$C$14:$C$28,"Site Work"),0) -> 0 | K34: =IFERROR(SUMIFS('Weekly Timesheet'!$M$14:$M$28,'Weekly Timesheet'!$C$14:$C$28,"Site Work")/(IFERROR(SUMIF('Weekly Timesheet'!$B$14:$B$28,"Project",'Weekly Timesheet'!$M$14:$M$28),1)),0) -> 0
E35: Report | H35: =IFERROR(SUMIFS('Weekly Timesheet'!$M$14:$M$28,'Weekly Timesheet'!$C$14:$C$28,"Report"),0) -> 2 | K35: =IFERROR(SUMIFS('Weekly Timesheet'!$M$14:$M$28,'Weekly Timesheet'!$C$14:$C$28,"Report")/(IFERROR(SUMIF('Weekly Timesheet'!$B$14:$B$28,"Project",'Weekly Timesheet'!$M$14:$M$28),1)),0) -> 0.2
E36: Extra Integration | H36: =IFERROR(SUMIFS('Weekly Timesheet'!$M$14:$M$28,'Weekly Timesheet'!$C$14:$C$28,"Extra Integration"),0) -> 0 | K36: =IFERROR(SUMIFS('Weekly Timesheet'!$M$14:$M$28,'Weekly Timesheet'!$C$14:$C$28,"Extra Integration")/(IFERROR(SUMIF('Weekly Timesheet'!$B$14:$B$28,"Project",'Weekly Timesheet'!$M$14:$M$28),1)),0) -> 0
E37: Simulation | H37: =IFERROR(SUMIFS('Weekly Timesheet'!$M$14:$M$28,'Weekly Timesheet'!$C$14:$C$28,"Simulation"),0) -> 0 | K37: =IFERROR(SUMIFS('Weekly Timesheet'!$M$14:$M$28,'Weekly Timesheet'!$C$14:$C$28,"Simulation")/(IFERROR(SUMIF('Weekly Timesheet'!$B$14:$B$28,"Project",'Weekly Timesheet'!$M$14:$M$28),1)),0) -> 0
E38: Office Preparation | H38: =IFERROR(SUMIFS('Weekly Timesheet'!$M$14:$M$28,'Weekly Timesheet'!$C$14:$C$28,"Office Preparation"),0) -> 0 | K38: =IFERROR(SUMIFS('Weekly Timesheet'!$M$14:$M$28,'Weekly Timesheet'!$C$14:$C$28,"Office Preparation")/(IFERROR(SUMIF('Weekly Timesheet'!$B$14:$B$28,"Project",'Weekly Timesheet'!$M$14:$M$28),1)),0) -> 0
E39: Project Management | H39: =IFERROR(SUMIFS('Weekly Timesheet'!$M$14:$M$28,'Weekly Timesheet'!$C$14:$C$28,"Project Management"),0) -> 0 | K39: =IFERROR(SUMIFS('Weekly Timesheet'!$M$14:$M$28,'Weekly Timesheet'!$C$14:$C$28,"Project Management")/(IFERROR(SUMIF('Weekly Timesheet'!$B$14:$B$28,"Project",'Weekly Timesheet'!$M$14:$M$28),1)),0) -> 0
E40: Engineering Work | H40: =IFERROR(SUMIFS('Weekly Timesheet'!$M$14:$M$28,'Weekly Timesheet'!$C$14:$C$28,"Engineering Work"),0) -> 0 | K40: =IFERROR(SUMIFS('Weekly Timesheet'!$M$14:$M$28,'Weekly Timesheet'!$C$14:$C$28,"Engineering Work")/(IFERROR(SUMIF('Weekly Timesheet'!$B$14:$B$28,"Project",'Weekly Timesheet'!$M$14:$M$28),1)),0) -> 0
B41: Admin | E41: Overtime Taken | H41: =IFERROR(SUMIFS('Weekly Timesheet'!$M$14:$M$28,'Weekly Timesheet'!$C$14:$C$28,"Overtime Taken"),0) -> 0 | K41: =IFERROR(SUMIFS('Weekly Timesheet'!$M$14:$M$28,'Weekly Timesheet'!$C$14:$C$28,"Overtime Taken")/(IFERROR(SUMIF('Weekly Timesheet'!$B$14:$B$28,"Admin",'Weekly Timesheet'!$M$14:$M$28),1)),0) -> 0
E42: TIL Payout | H42: =IFERROR(SUMIFS('Weekly Timesheet'!$M$14:$M$28,'Weekly Timesheet'!$C$14:$C$28,"TIL Payout"),0) -> 20 | K42: =IFERROR(SUMIFS('Weekly Timesheet'!$M$14:$M$28,'Weekly Timesheet'!$C$14:$C$28,"TIL Payout")/(IFERROR(SUMIF('Weekly Timesheet'!$B$14:$B$28,"Admin",'Weekly Timesheet'!$M$14:$M$28),1)),0) -> 0.68965517
E43: Sick Time | H43: =IFERROR(SUMIFS('Weekly Timesheet'!$M$14:$M$28,'Weekly Timesheet'!$C$14:$C$28,"Sick Time"),0) -> 0 | K43: =IFERROR(SUMIFS('Weekly Timesheet'!$M$14:$M$28,'Weekly Timesheet'!$C$14:$C$28,"Sick Time")/(IFERROR(SUMIF('Weekly Timesheet'!$B$14:$B$28,"Admin",'Weekly Timesheet'!$M$14:$M$28),1)),0) -> 0
E44: Vacation Hours | H44: =IFERROR(SUMIFS('Weekly Timesheet'!$M$14:$M$28,'Weekly Timesheet'!$C$14:$C$28,"Vacation Hours"),0) -> 0 | K44: =IFERROR(SUMIFS('Weekly Timesheet'!$M$14:$M$28,'Weekly Timesheet'!$C$14:$C$28,"Vacation Hours")/(IFERROR(SUMIF('Weekly Timesheet'!$B$14:$B$28,"Admin",'Weekly Timesheet'!$M$14:$M$28),1)),0) -> 0
E45: Statutory Holiday | H45: =IFERROR(SUMIFS('Weekly Timesheet'!$M$14:$M$28,'Weekly Timesheet'!$C$14:$C$28,"Statutory Holiday"),0) -> 8 | K45: =IFERROR(SUMIFS('Weekly Timesheet'!$M$14:$M$28,'Weekly Timesheet'!$C$14:$C$28,"Statutory Holiday")/(IFERROR(SUMIF('Weekly Timesheet'!$B$14:$B$28,"Admin",'Weekly Timesheet'!$M$14:$M$28),1)),0) -> 0.27586207
E46: Administrative | H46: =IFERROR(SUMIFS('Weekly Timesheet'!$M$14:$M$28,'Weekly Timesheet'!$C$14:$C$28,"Administrative"),0) -> 0 | K46: =IFERROR(SUMIFS('Weekly Timesheet'!$M$14:$M$28,'Weekly Timesheet'!$C$14:$C$28,"Administrative")/(IFERROR(SUMIF('Weekly Timesheet'!$B$14:$B$28,"Admin",'Weekly Timesheet'!$M$14:$M$28),1)),0) -> 0
E47: Toolbox Meeting | H47: =IFERROR(SUMIFS('Weekly Timesheet'!$M$14:$M$28,'Weekly Timesheet'!$C$14:$C$28,"Toolbox Meeting"),0) -> 1 | K47: =IFERROR(SUMIFS('Weekly Timesheet'!$M$14:$M$28,'Weekly Timesheet'!$C$14:$C$28,"Toolbox Meeting")/(IFERROR(SUMIF('Weekly Timesheet'!$B$14:$B$28,"Admin",'Weekly Timesheet'!$M$14:$M$28),1)),0) -> 0.034482759
B48: Office & Sales | E48: Customer Contact | H48: =IFERROR(SUMIFS('Weekly Timesheet'!$M$14:$M$28,'Weekly Timesheet'!$C$14:$C$28,"Customer Contact"),0) -> 0 | K48: =IFERROR(SUMIFS('Weekly Timesheet'!$M$14:$M$28,'Weekly Timesheet'!$C$14:$C$28,"Customer Contact")/(IFERROR(SUMIF('Weekly Timesheet'!$B$14:$B$28,"Office & Sales",'Weekly Timesheet'!$M$14:$M$28),1)),0) -> 0
E49: Project Development | H49: =IFERROR(SUMIFS('Weekly Timesheet'!$M$14:$M$28,'Weekly Timesheet'!$C$14:$C$28,"Project Development"),0) -> 0 | K49: =IFERROR(SUMIFS('Weekly Timesheet'!$M$14:$M$28,'Weekly Timesheet'!$C$14:$C$28,"Project Development")/(IFERROR(SUMIF('Weekly Timesheet'!$B$14:$B$28,"Office & Sales",'Weekly Timesheet'!$M$14:$M$28),1)),0) -> 0
E50: Proposals & Quotes | H50: =IFERROR(SUMIFS('Weekly Timesheet'!$M$14:$M$28,'Weekly Timesheet'!$C$14:$C$28,"Proposals & Quotes"),0) -> 0 | K50: =IFERROR(SUMIFS('Weekly Timesheet'!$M$14:$M$28,'Weekly Timesheet'!$C$14:$C$28,"Proposals & Quotes")/(IFERROR(SUMIF('Weekly Timesheet'!$B$14:$B$28,"Office & Sales",'Weekly Timesheet'!$M$14:$M$28),1)),0) -> 0
E51: Inventory | H51: =IFERROR(SUMIFS('Weekly Timesheet'!$M$14:$M$28,'Weekly Timesheet'!$C$14:$C$28,"Inventory"),0) -> 0 | K51: =IFERROR(SUMIFS('Weekly Timesheet'!$M$14:$M$28,'Weekly Timesheet'!$C$14:$C$28,"Inventory")/(IFERROR(SUMIF('Weekly Timesheet'!$B$14:$B$28,"Office & Sales",'Weekly Timesheet'!$M$14:$M$28),1)),0) -> 0
E52: SRU Study | H52: =IFERROR(SUMIFS('Weekly Timesheet'!$M$14:$M$28,'Weekly Timesheet'!$C$14:$C$28,"SRU Study"),0) -> 0 | K52: =IFERROR(SUMIFS('Weekly Timesheet'!$M$14:$M$28,'Weekly Timesheet'!$C$14:$C$28,"SRU Study")/(IFERROR(SUMIF('Weekly Timesheet'!$B$14:$B$28,"Office & Sales",'Weekly Timesheet'!$M$14:$M$28),1)),0) -> 0
E53: Conference | H53: =IFERROR(SUMIFS('Weekly Timesheet'!$M$14:$M$28,'Weekly Timesheet'!$C$14:$C$28,"Conference"),0) -> 0 | K53: =IFERROR(SUMIFS('Weekly Timesheet'!$M$14:$M$28,'Weekly Timesheet'!$C$14:$C$28,"Conference")/(IFERROR(SUMIF('Weekly Timesheet'!$B$14:$B$28,"Office & Sales",'Weekly Timesheet'!$M$14:$M$28),1)),0) -> 0
E54: General | H54: =IFERROR(SUMIFS('Weekly Timesheet'!$M$14:$M$28,'Weekly Timesheet'!$C$14:$C$28,"General"),0) -> 21 | K54: =IFERROR(SUMIFS('Weekly Timesheet'!$M$14:$M$28,'Weekly Timesheet'!$C$14:$C$28,"General")/(IFERROR(SUMIF('Weekly Timesheet'!$B$14:$B$28,"Office & Sales",'Weekly Timesheet'!$M$14:$M$28),1)),0) -> 1
B56: HOURS BY PROJECT NUMBER
B58: Project No. | E58: Sub-Category | H58: Mon | I58: Tue | J58: Wed | K58: Thu | L58: Fri | M58: Sat | N58: Total hrs
B59: {=IFERROR(INDEX(_xlfn._xlws.SORT(_xlfn.UNIQUE(_xlfn._xlws.FILTER('Weekly Timesheet'!$D$14:$D$28,'Weekly Timesheet'!$B$14:$B$28="Project"))),1),"")} -> 2026125 | E59: {=IFERROR(IF(B59="","",INDEX('Weekly Timesheet'!$C$14:$C$28,MATCH(1,('Weekly Timesheet'!$B$14:$B$28="Project")*('Weekly Timesheet'!$D$14:$D$28=B59),0))),"")} -> Site Travel | H59: =IFERROR(IF(B59="","",SUMIFS('Weekly Timesheet'!$E$14:$E$28,'Weekly Timesheet'!$B$14:$B$28,"Project",'Weekly Timesheet'!$D$14:$D$28,B59)),"") -> 8 | I59: =IFERROR(IF(B59="","",SUMIFS('Weekly Timesheet'!$F$14:$F$28,'Weekly Timesheet'!$B$14:$B$28,"Project",'Weekly Timesheet'!$D$14:$D$28,B59)),"") -> 0 | J59: =IFERROR(IF(B59="","",SUMIFS('Weekly Timesheet'!$G$14:$G$28,'Weekly Timesheet'!$B$14:$B$28,"Project",'Weekly Timesheet'!$D$14:$D$28,B59)),"") -> 0 | K59: =IFERROR(IF(B59="","",SUMIFS('Weekly Timesheet'!$H$14:$H$28,'Weekly Timesheet'!$B$14:$B$28,"Project",'Weekly Timesheet'!$D$14:$D$28,B59)),"") -> 2 | L59: =IFERROR(IF(B59="","",SUMIFS('Weekly Timesheet'!$I$14:$I$28,'Weekly Timesheet'!$B$14:$B$28,"Project",'Weekly Timesheet'!$D$14:$D$28,B59)),"") -> 0 | M59: =IFERROR(IF(B59="","",SUMIFS('Weekly Timesheet'!$J$14:$J$28,'Weekly Timesheet'!$B$14:$B$28,"Project",'Weekly Timesheet'!$D$14:$D$28,B59)),"") -> 0 | N59: =IFERROR(IF(B59="","",SUMIFS('Weekly Timesheet'!$M$14:$M$28,'Weekly Timesheet'!$B$14:$B$28,"Project",'Weekly Timesheet'!$D$14:$D$28,B59)),"") -> 10
B60: {=IFERROR(INDEX(_xlfn._xlws.SORT(_xlfn.UNIQUE(_xlfn._xlws.FILTER('Weekly Timesheet'!$D$14:$D$28,'Weekly Timesheet'!$B$14:$B$28="Project"))),2),"")} | E60: {=IFERROR(IF(B60="","",INDEX('Weekly Timesheet'!$C$14:$C$28,MATCH(1,('Weekly Timesheet'!$B$14:$B$28="Project")*('Weekly Timesheet'!$D$14:$D$28=B60),0))),"")} | H60: =IFERROR(IF(B60="","",SUMIFS('Weekly Timesheet'!$E$14:$E$28,'Weekly Timesheet'!$B$14:$B$28,"Project",'Weekly Timesheet'!$D$14:$D$28,B60)),"") | I60: =IFERROR(IF(B60="","",SUMIFS('Weekly Timesheet'!$F$14:$F$28,'Weekly Timesheet'!$B$14:$B$28,"Project",'Weekly Timesheet'!$D$14:$D$28,B60)),"") | J60: =IFERROR(IF(B60="","",SUMIFS('Weekly Timesheet'!$G$14:$G$28,'Weekly Timesheet'!$B$14:$B$28,"Project",'Weekly Timesheet'!$D$14:$D$28,B60)),"") | K60: =IFERROR(IF(B60="","",SUMIFS('Weekly Timesheet'!$H$14:$H$28,'Weekly Timesheet'!$B$14:$B$28,"Project",'Weekly Timesheet'!$D$14:$D$28,B60)),"") | L60: =IFERROR(IF(B60="","",SUMIFS('Weekly Timesheet'!$I$14:$I$28,'Weekly Timesheet'!$B$14:$B$28,"Project",'Weekly Timesheet'!$D$14:$D$28,B60)),"") | M60: =IFERROR(IF(B60="","",SUMIFS('Weekly Timesheet'!$J$14:$J$28,'Weekly Timesheet'!$B$14:$B$28,"Project",'Weekly Timesheet'!$D$14:$D$28,B60)),"") | N60: =IFERROR(IF(B60="","",SUMIFS('Weekly Timesheet'!$M$14:$M$28,'Weekly Timesheet'!$B$14:$B$28,"Project",'Weekly Timesheet'!$D$14:$D$28,B60)),"")
B61: {=IFERROR(INDEX(_xlfn._xlws.SORT(_xlfn.UNIQUE(_xlfn._xlws.FILTER('Weekly Timesheet'!$D$14:$D$28,'Weekly Timesheet'!$B$14:$B$28="Project"))),3),"")} | E61: {=IFERROR(IF(B61="","",INDEX('Weekly Timesheet'!$C$14:$C$28,MATCH(1,('Weekly Timesheet'!$B$14:$B$28="Project")*('Weekly Timesheet'!$D$14:$D$28=B61),0))),"")} | H61: =IFERROR(IF(B61="","",SUMIFS('Weekly Timesheet'!$E$14:$E$28,'Weekly Timesheet'!$B$14:$B$28,"Project",'Weekly Timesheet'!$D$14:$D$28,B61)),"") | I61: =IFERROR(IF(B61="","",SUMIFS('Weekly Timesheet'!$F$14:$F$28,'Weekly Timesheet'!$B$14:$B$28,"Project",'Weekly Timesheet'!$D$14:$D$28,B61)),"") | J61: =IFERROR(IF(B61="","",SUMIFS('Weekly Timesheet'!$G$14:$G$28,'Weekly Timesheet'!$B$14:$B$28,"Project",'Weekly Timesheet'!$D$14:$D$28,B61)),"") | K61: =IFERROR(IF(B61="","",SUMIFS('Weekly Timesheet'!$H$14:$H$28,'Weekly Timesheet'!$B$14:$B$28,"Project",'Weekly Timesheet'!$D$14:$D$28,B61)),"") | L61: =IFERROR(IF(B61="","",SUMIFS('Weekly Timesheet'!$I$14:$I$28,'Weekly Timesheet'!$B$14:$B$28,"Project",'Weekly Timesheet'!$D$14:$D$28,B61)),"") | M61: =IFERROR(IF(B61="","",SUMIFS('Weekly Timesheet'!$J$14:$J$28,'Weekly Timesheet'!$B$14:$B$28,"Project",'Weekly Timesheet'!$D$14:$D$28,B61)),"") | N61: =IFERROR(IF(B61="","",SUMIFS('Weekly Timesheet'!$M$14:$M$28,'Weekly Timesheet'!$B$14:$B$28,"Project",'Weekly Timesheet'!$D$14:$D$28,B61)),"")
B62: {=IFERROR(INDEX(_xlfn._xlws.SORT(_xlfn.UNIQUE(_xlfn._xlws.FILTER('Weekly Timesheet'!$D$14:$D$28,'Weekly Timesheet'!$B$14:$B$28="Project"))),4),"")} | E62: {=IFERROR(IF(B62="","",INDEX('Weekly Timesheet'!$C$14:$C$28,MATCH(1,('Weekly Timesheet'!$B$14:$B$28="Project")*('Weekly Timesheet'!$D$14:$D$28=B62),0))),"")} | H62: =IFERROR(IF(B62="","",SUMIFS('Weekly Timesheet'!$E$14:$E$28,'Weekly Timesheet'!$B$14:$B$28,"Project",'Weekly Timesheet'!$D$14:$D$28,B62)),"") | I62: =IFERROR(IF(B62="","",SUMIFS('Weekly Timesheet'!$F$14:$F$28,'Weekly Timesheet'!$B$14:$B$28,"Project",'Weekly Timesheet'!$D$14:$D$28,B62)),"") | J62: =IFERROR(IF(B62="","",SUMIFS('Weekly Timesheet'!$G$14:$G$28,'Weekly Timesheet'!$B$14:$B$28,"Project",'Weekly Timesheet'!$D$14:$D$28,B62)),"") | K62: =IFERROR(IF(B62="","",SUMIFS('Weekly Timesheet'!$H$14:$H$28,'Weekly Timesheet'!$B$14:$B$28,"Project",'Weekly Timesheet'!$D$14:$D$28,B62)),"") | L62: =IFERROR(IF(B62="","",SUMIFS('Weekly Timesheet'!$I$14:$I$28,'Weekly Timesheet'!$B$14:$B$28,"Project",'Weekly Timesheet'!$D$14:$D$28,B62)),"") | M62: =IFERROR(IF(B62="","",SUMIFS('Weekly Timesheet'!$J$14:$J$28,'Weekly Timesheet'!$B$14:$B$28,"Project",'Weekly Timesheet'!$D$14:$D$28,B62)),"") | N62: =IFERROR(IF(B62="","",SUMIFS('Weekly Timesheet'!$M$14:$M$28,'Weekly Timesheet'!$B$14:$B$28,"Project",'Weekly Timesheet'!$D$14:$D$28,B62)),"")
B63: {=IFERROR(INDEX(_xlfn._xlws.SORT(_xlfn.UNIQUE(_xlfn._xlws.FILTER('Weekly Timesheet'!$D$14:$D$28,'Weekly Timesheet'!$B$14:$B$28="Project"))),5),"")} | E63: {=IFERROR(IF(B63="","",INDEX('Weekly Timesheet'!$C$14:$C$28,MATCH(1,('Weekly Timesheet'!$B$14:$B$28="Project")*('Weekly Timesheet'!$D$14:$D$28=B63),0))),"")} | H63: =IFERROR(IF(B63="","",SUMIFS('Weekly Timesheet'!$E$14:$E$28,'Weekly Timesheet'!$B$14:$B$28,"Project",'Weekly Timesheet'!$D$14:$D$28,B63)),"") | I63: =IFERROR(IF(B63="","",SUMIFS('Weekly Timesheet'!$F$14:$F$28,'Weekly Timesheet'!$B$14:$B$28,"Project",'Weekly Timesheet'!$D$14:$D$28,B63)),"") | J63: =IFERROR(IF(B63="","",SUMIFS('Weekly Timesheet'!$G$14:$G$28,'Weekly Timesheet'!$B$14:$B$28,"Project",'Weekly Timesheet'!$D$14:$D$28,B63)),"") | K63: =IFERROR(IF(B63="","",SUMIFS('Weekly Timesheet'!$H$14:$H$28,'Weekly Timesheet'!$B$14:$B$28,"Project",'Weekly Timesheet'!$D$14:$D$28,B63)),"") | L63: =IFERROR(IF(B63="","",SUMIFS('Weekly Timesheet'!$I$14:$I$28,'Weekly Timesheet'!$B$14:$B$28,"Project",'Weekly Timesheet'!$D$14:$D$28,B63)),"") | M63: =IFERROR(IF(B63="","",SUMIFS('Weekly Timesheet'!$J$14:$J$28,'Weekly Timesheet'!$B$14:$B$28,"Project",'Weekly Timesheet'!$D$14:$D$28,B63)),"") | N63: =IFERROR(IF(B63="","",SUMIFS('Weekly Timesheet'!$M$14:$M$28,'Weekly Timesheet'!$B$14:$B$28,"Project",'Weekly Timesheet'!$D$14:$D$28,B63)),"")
B64: {=IFERROR(INDEX(_xlfn._xlws.SORT(_xlfn.UNIQUE(_xlfn._xlws.FILTER('Weekly Timesheet'!$D$14:$D$28,'Weekly Timesheet'!$B$14:$B$28="Project"))),6),"")} | E64: {=IFERROR(IF(B64="","",INDEX('Weekly Timesheet'!$C$14:$C$28,MATCH(1,('Weekly Timesheet'!$B$14:$B$28="Project")*('Weekly Timesheet'!$D$14:$D$28=B64),0))),"")} | H64: =IFERROR(IF(B64="","",SUMIFS('Weekly Timesheet'!$E$14:$E$28,'Weekly Timesheet'!$B$14:$B$28,"Project",'Weekly Timesheet'!$D$14:$D$28,B64)),"") | I64: =IFERROR(IF(B64="","",SUMIFS('Weekly Timesheet'!$F$14:$F$28,'Weekly Timesheet'!$B$14:$B$28,"Project",'Weekly Timesheet'!$D$14:$D$28,B64)),"") | J64: =IFERROR(IF(B64="","",SUMIFS('Weekly Timesheet'!$G$14:$G$28,'Weekly Timesheet'!$B$14:$B$28,"Project",'Weekly Timesheet'!$D$14:$D$28,B64)),"") | K64: =IFERROR(IF(B64="","",SUMIFS('Weekly Timesheet'!$H$14:$H$28,'Weekly Timesheet'!$B$14:$B$28,"Project",'Weekly Timesheet'!$D$14:$D$28,B64)),"") | L64: =IFERROR(IF(B64="","",SUMIFS('Weekly Timesheet'!$I$14:$I$28,'Weekly Timesheet'!$B$14:$B$28,"Project",'Weekly Timesheet'!$D$14:$D$28,B64)),"") | M64: =IFERROR(IF(B64="","",SUMIFS('Weekly Timesheet'!$J$14:$J$28,'Weekly Timesheet'!$B$14:$B$28,"Project",'Weekly Timesheet'!$D$14:$D$28,B64)),"") | N64: =IFERROR(IF(B64="","",SUMIFS('Weekly Timesheet'!$M$14:$M$28,'Weekly Timesheet'!$B$14:$B$28,"Project",'Weekly Timesheet'!$D$14:$D$28,B64)),"")
B65: {=IFERROR(INDEX(_xlfn._xlws.SORT(_xlfn.UNIQUE(_xlfn._xlws.FILTER('Weekly Timesheet'!$D$14:$D$28,'Weekly Timesheet'!$B$14:$B$28="Project"))),7),"")} | E65: {=IFERROR(IF(B65="","",INDEX('Weekly Timesheet'!$C$14:$C$28,MATCH(1,('Weekly Timesheet'!$B$14:$B$28="Project")*('Weekly Timesheet'!$D$14:$D$28=B65),0))),"")} | H65: =IFERROR(IF(B65="","",SUMIFS('Weekly Timesheet'!$E$14:$E$28,'Weekly Timesheet'!$B$14:$B$28,"Project",'Weekly Timesheet'!$D$14:$D$28,B65)),"") | I65: =IFERROR(IF(B65="","",SUMIFS('Weekly Timesheet'!$F$14:$F$28,'Weekly Timesheet'!$B$14:$B$28,"Project",'Weekly Timesheet'!$D$14:$D$28,B65)),"") | J65: =IFERROR(IF(B65="","",SUMIFS('Weekly Timesheet'!$G$14:$G$28,'Weekly Timesheet'!$B$14:$B$28,"Project",'Weekly Timesheet'!$D$14:$D$28,B65)),"") | K65: =IFERROR(IF(B65="","",SUMIFS('Weekly Timesheet'!$H$14:$H$28,'Weekly Timesheet'!$B$14:$B$28,"Project",'Weekly Timesheet'!$D$14:$D$28,B65)),"") | L65: =IFERROR(IF(B65="","",SUMIFS('Weekly Timesheet'!$I$14:$I$28,'Weekly Timesheet'!$B$14:$B$28,"Project",'Weekly Timesheet'!$D$14:$D$28,B65)),"") | M65: =IFERROR(IF(B65="","",SUMIFS('Weekly Timesheet'!$J$14:$J$28,'Weekly Timesheet'!$B$14:$B$28,"Project",'Weekly Timesheet'!$D$14:$D$28,B65)),"") | N65: =IFERROR(IF(B65="","",SUMIFS('Weekly Timesheet'!$M$14:$M$28,'Weekly Timesheet'!$B$14:$B$28,"Project",'Weekly Timesheet'!$D$14:$D$28,B65)),"")
B66: {=IFERROR(INDEX(_xlfn._xlws.SORT(_xlfn.UNIQUE(_xlfn._xlws.FILTER('Weekly Timesheet'!$D$14:$D$28,'Weekly Timesheet'!$B$14:$B$28="Project"))),8),"")} | E66: {=IFERROR(IF(B66="","",INDEX('Weekly Timesheet'!$C$14:$C$28,MATCH(1,('Weekly Timesheet'!$B$14:$B$28="Project")*('Weekly Timesheet'!$D$14:$D$28=B66),0))),"")} | H66: =IFERROR(IF(B66="","",SUMIFS('Weekly Timesheet'!$E$14:$E$28,'Weekly Timesheet'!$B$14:$B$28,"Project",'Weekly Timesheet'!$D$14:$D$28,B66)),"") | I66: =IFERROR(IF(B66="","",SUMIFS('Weekly Timesheet'!$F$14:$F$28,'Weekly Timesheet'!$B$14:$B$28,"Project",'Weekly Timesheet'!$D$14:$D$28,B66)),"") | J66: =IFERROR(IF(B66="","",SUMIFS('Weekly Timesheet'!$G$14:$G$28,'Weekly Timesheet'!$B$14:$B$28,"Project",'Weekly Timesheet'!$D$14:$D$28,B66)),"") | K66: =IFERROR(IF(B66="","",SUMIFS('Weekly Timesheet'!$H$14:$H$28,'Weekly Timesheet'!$B$14:$B$28,"Project",'Weekly Timesheet'!$D$14:$D$28,B66)),"") | L66: =IFERROR(IF(B66="","",SUMIFS('Weekly Timesheet'!$I$14:$I$28,'Weekly Timesheet'!$B$14:$B$28,"Project",'Weekly Timesheet'!$D$14:$D$28,B66)),"") | M66: =IFERROR(IF(B66="","",SUMIFS('Weekly Timesheet'!$J$14:$J$28,'Weekly Timesheet'!$B$14:$B$28,"Project",'Weekly Timesheet'!$D$14:$D$28,B66)),"") | N66: =IFERROR(IF(B66="","",SUMIFS('Weekly Timesheet'!$M$14:$M$28,'Weekly Timesheet'!$B$14:$B$28,"Project",'Weekly Timesheet'!$D$14:$D$28,B66)),"")
B67: {=IFERROR(INDEX(_xlfn._xlws.SORT(_xlfn.UNIQUE(_xlfn._xlws.FILTER('Weekly Timesheet'!$D$14:$D$28,'Weekly Timesheet'!$B$14:$B$28="Project"))),9),"")} | E67: {=IFERROR(IF(B67="","",INDEX('Weekly Timesheet'!$C$14:$C$28,MATCH(1,('Weekly Timesheet'!$B$14:$B$28="Project")*('Weekly Timesheet'!$D$14:$D$28=B67),0))),"")} | H67: =IFERROR(IF(B67="","",SUMIFS('Weekly Timesheet'!$E$14:$E$28,'Weekly Timesheet'!$B$14:$B$28,"Project",'Weekly Timesheet'!$D$14:$D$28,B67)),"") | I67: =IFERROR(IF(B67="","",SUMIFS('Weekly Timesheet'!$F$14:$F$28,'Weekly Timesheet'!$B$14:$B$28,"Project",'Weekly Timesheet'!$D$14:$D$28,B67)),"") | J67: =IFERROR(IF(B67="","",SUMIFS('Weekly Timesheet'!$G$14:$G$28,'Weekly Timesheet'!$B$14:$B$28,"Project",'Weekly Timesheet'!$D$14:$D$28,B67)),"") | K67: =IFERROR(IF(B67="","",SUMIFS('Weekly Timesheet'!$H$14:$H$28,'Weekly Timesheet'!$B$14:$B$28,"Project",'Weekly Timesheet'!$D$14:$D$28,B67)),"") | L67: =IFERROR(IF(B67="","",SUMIFS('Weekly Timesheet'!$I$14:$I$28,'Weekly Timesheet'!$B$14:$B$28,"Project",'Weekly Timesheet'!$D$14:$D$28,B67)),"") | M67: =IFERROR(IF(B67="","",SUMIFS('Weekly Timesheet'!$J$14:$J$28,'Weekly Timesheet'!$B$14:$B$28,"Project",'Weekly Timesheet'!$D$14:$D$28,B67)),"") | N67: =IFERROR(IF(B67="","",SUMIFS('Weekly Timesheet'!$M$14:$M$28,'Weekly Timesheet'!$B$14:$B$28,"Project",'Weekly Timesheet'!$D$14:$D$28,B67)),"")
B68: {=IFERROR(INDEX(_xlfn._xlws.SORT(_xlfn.UNIQUE(_xlfn._xlws.FILTER('Weekly Timesheet'!$D$14:$D$28,'Weekly Timesheet'!$B$14:$B$28="Project"))),10),"")} | E68: {=IFERROR(IF(B68="","",INDEX('Weekly Timesheet'!$C$14:$C$28,MATCH(1,('Weekly Timesheet'!$B$14:$B$28="Project")*('Weekly Timesheet'!$D$14:$D$28=B68),0))),"")} | H68: =IFERROR(IF(B68="","",SUMIFS('Weekly Timesheet'!$E$14:$E$28,'Weekly Timesheet'!$B$14:$B$28,"Project",'Weekly Timesheet'!$D$14:$D$28,B68)),"") | I68: =IFERROR(IF(B68="","",SUMIFS('Weekly Timesheet'!$F$14:$F$28,'Weekly Timesheet'!$B$14:$B$28,"Project",'Weekly Timesheet'!$D$14:$D$28,B68)),"") | J68: =IFERROR(IF(B68="","",SUMIFS('Weekly Timesheet'!$G$14:$G$28,'Weekly Timesheet'!$B$14:$B$28,"Project",'Weekly Timesheet'!$D$14:$D$28,B68)),"") | K68: =IFERROR(IF(B68="","",SUMIFS('Weekly Timesheet'!$H$14:$H$28,'Weekly Timesheet'!$B$14:$B$28,"Project",'Weekly Timesheet'!$D$14:$D$28,B68)),"") | L68: =IFERROR(IF(B68="","",SUMIFS('Weekly Timesheet'!$I$14:$I$28,'Weekly Timesheet'!$B$14:$B$28,"Project",'Weekly Timesheet'!$D$14:$D$28,B68)),"") | M68: =IFERROR(IF(B68="","",SUMIFS('Weekly Timesheet'!$J$14:$J$28,'Weekly Timesheet'!$B$14:$B$28,"Project",'Weekly Timesheet'!$D$14:$D$28,B68)),"") | N68: =IFERROR(IF(B68="","",SUMIFS('Weekly Timesheet'!$M$14:$M$28,'Weekly Timesheet'!$B$14:$B$28,"Project",'Weekly Timesheet'!$D$14:$D$28,B68)),"")
B69: {=IFERROR(INDEX(_xlfn._xlws.SORT(_xlfn.UNIQUE(_xlfn._xlws.FILTER('Weekly Timesheet'!$D$14:$D$28,'Weekly Timesheet'!$B$14:$B$28="Project"))),11),"")} | E69: {=IFERROR(IF(B69="","",INDEX('Weekly Timesheet'!$C$14:$C$28,MATCH(1,('Weekly Timesheet'!$B$14:$B$28="Project")*('Weekly Timesheet'!$D$14:$D$28=B69),0))),"")} | H69: =IFERROR(IF(B69="","",SUMIFS('Weekly Timesheet'!$E$14:$E$28,'Weekly Timesheet'!$B$14:$B$28,"Project",'Weekly Timesheet'!$D$14:$D$28,B69)),"") | I69: =IFERROR(IF(B69="","",SUMIFS('Weekly Timesheet'!$F$14:$F$28,'Weekly Timesheet'!$B$14:$B$28,"Project",'Weekly Timesheet'!$D$14:$D$28,B69)),"") | J69: =IFERROR(IF(B69="","",SUMIFS('Weekly Timesheet'!$G$14:$G$28,'Weekly Timesheet'!$B$14:$B$28,"Project",'Weekly Timesheet'!$D$14:$D$28,B69)),"") | K69: =IFERROR(IF(B69="","",SUMIFS('Weekly Timesheet'!$H$14:$H$28,'Weekly Timesheet'!$B$14:$B$28,"Project",'Weekly Timesheet'!$D$14:$D$28,B69)),"") | L69: =IFERROR(IF(B69="","",SUMIFS('Weekly Timesheet'!$I$14:$I$28,'Weekly Timesheet'!$B$14:$B$28,"Project",'Weekly Timesheet'!$D$14:$D$28,B69)),"") | M69: =IFERROR(IF(B69="","",SUMIFS('Weekly Timesheet'!$J$14:$J$28,'Weekly Timesheet'!$B$14:$B$28,"Project",'Weekly Timesheet'!$D$14:$D$28,B69)),"") | N69: =IFERROR(IF(B69="","",SUMIFS('Weekly Timesheet'!$M$14:$M$28,'Weekly Timesheet'!$B$14:$B$28,"Project",'Weekly Timesheet'!$D$14:$D$28,B69)),"")
B70: {=IFERROR(INDEX(_xlfn._xlws.SORT(_xlfn.UNIQUE(_xlfn._xlws.FILTER('Weekly Timesheet'!$D$14:$D$28,'Weekly Timesheet'!$B$14:$B$28="Project"))),12),"")} | E70: {=IFERROR(IF(B70="","",INDEX('Weekly Timesheet'!$C$14:$C$28,MATCH(1,('Weekly Timesheet'!$B$14:$B$28="Project")*('Weekly Timesheet'!$D$14:$D$28=B70),0))),"")} | H70: =IFERROR(IF(B70="","",SUMIFS('Weekly Timesheet'!$E$14:$E$28,'Weekly Timesheet'!$B$14:$B$28,"Project",'Weekly Timesheet'!$D$14:$D$28,B70)),"") | I70: =IFERROR(IF(B70="","",SUMIFS('Weekly Timesheet'!$F$14:$F$28,'Weekly Timesheet'!$B$14:$B$28,"Project",'Weekly Timesheet'!$D$14:$D$28,B70)),"") | J70: =IFERROR(IF(B70="","",SUMIFS('Weekly Timesheet'!$G$14:$G$28,'Weekly Timesheet'!$B$14:$B$28,"Project",'Weekly Timesheet'!$D$14:$D$28,B70)),"") | K70: =IFERROR(IF(B70="","",SUMIFS('Weekly Timesheet'!$H$14:$H$28,'Weekly Timesheet'!$B$14:$B$28,"Project",'Weekly Timesheet'!$D$14:$D$28,B70)),"") | L70: =IFERROR(IF(B70="","",SUMIFS('Weekly Timesheet'!$I$14:$I$28,'Weekly Timesheet'!$B$14:$B$28,"Project",'Weekly Timesheet'!$D$14:$D$28,B70)),"") | M70: =IFERROR(IF(B70="","",SUMIFS('Weekly Timesheet'!$J$14:$J$28,'Weekly Timesheet'!$B$14:$B$28,"Project",'Weekly Timesheet'!$D$14:$D$28,B70)),"") | N70: =IFERROR(IF(B70="","",SUMIFS('Weekly Timesheet'!$M$14:$M$28,'Weekly Timesheet'!$B$14:$B$28,"Project",'Weekly Timesheet'!$D$14:$D$28,B70)),"")
B71: {=IFERROR(INDEX(_xlfn._xlws.SORT(_xlfn.UNIQUE(_xlfn._xlws.FILTER('Weekly Timesheet'!$D$14:$D$28,'Weekly Timesheet'!$B$14:$B$28="Project"))),13),"")} | E71: {=IFERROR(IF(B71="","",INDEX('Weekly Timesheet'!$C$14:$C$28,MATCH(1,('Weekly Timesheet'!$B$14:$B$28="Project")*('Weekly Timesheet'!$D$14:$D$28=B71),0))),"")} | H71: =IFERROR(IF(B71="","",SUMIFS('Weekly Timesheet'!$E$14:$E$28,'Weekly Timesheet'!$B$14:$B$28,"Project",'Weekly Timesheet'!$D$14:$D$28,B71)),"") | I71: =IFERROR(IF(B71="","",SUMIFS('Weekly Timesheet'!$F$14:$F$28,'Weekly Timesheet'!$B$14:$B$28,"Project",'Weekly Timesheet'!$D$14:$D$28,B71)),"") | J71: =IFERROR(IF(B71="","",SUMIFS('Weekly Timesheet'!$G$14:$G$28,'Weekly Timesheet'!$B$14:$B$28,"Project",'Weekly Timesheet'!$D$14:$D$28,B71)),"") | K71: =IFERROR(IF(B71="","",SUMIFS('Weekly Timesheet'!$H$14:$H$28,'Weekly Timesheet'!$B$14:$B$28,"Project",'Weekly Timesheet'!$D$14:$D$28,B71)),"") | L71: =IFERROR(IF(B71="","",SUMIFS('Weekly Timesheet'!$I$14:$I$28,'Weekly Timesheet'!$B$14:$B$28,"Project",'Weekly Timesheet'!$D$14:$D$28,B71)),"") | M71: =IFERROR(IF(B71="","",SUMIFS('Weekly Timesheet'!$J$14:$J$28,'Weekly Timesheet'!$B$14:$B$28,"Project",'Weekly Timesheet'!$D$14:$D$28,B71)),"") | N71: =IFERROR(IF(B71="","",SUMIFS('Weekly Timesheet'!$M$14:$M$28,'Weekly Timesheet'!$B$14:$B$28,"Project",'Weekly Timesheet'!$D$14:$D$28,B71)),"")
B72: {=IFERROR(INDEX(_xlfn._xlws.SORT(_xlfn.UNIQUE(_xlfn._xlws.FILTER('Weekly Timesheet'!$D$14:$D$28,'Weekly Timesheet'!$B$14:$B$28="Project"))),14),"")} | E72: {=IFERROR(IF(B72="","",INDEX('Weekly Timesheet'!$C$14:$C$28,MATCH(1,('Weekly Timesheet'!$B$14:$B$28="Project")*('Weekly Timesheet'!$D$14:$D$28=B72),0))),"")} | H72: =IFERROR(IF(B72="","",SUMIFS('Weekly Timesheet'!$E$14:$E$28,'Weekly Timesheet'!$B$14:$B$28,"Project",'Weekly Timesheet'!$D$14:$D$28,B72)),"") | I72: =IFERROR(IF(B72="","",SUMIFS('Weekly Timesheet'!$F$14:$F$28,'Weekly Timesheet'!$B$14:$B$28,"Project",'Weekly Timesheet'!$D$14:$D$28,B72)),"") | J72: =IFERROR(IF(B72="","",SUMIFS('Weekly Timesheet'!$G$14:$G$28,'Weekly Timesheet'!$B$14:$B$28,"Project",'Weekly Timesheet'!$D$14:$D$28,B72)),"") | K72: =IFERROR(IF(B72="","",SUMIFS('Weekly Timesheet'!$H$14:$H$28,'Weekly Timesheet'!$B$14:$B$28,"Project",'Weekly Timesheet'!$D$14:$D$28,B72)),"") | L72: =IFERROR(IF(B72="","",SUMIFS('Weekly Timesheet'!$I$14:$I$28,'Weekly Timesheet'!$B$14:$B$28,"Project",'Weekly Timesheet'!$D$14:$D$28,B72)),"") | M72: =IFERROR(IF(B72="","",SUMIFS('Weekly Timesheet'!$J$14:$J$28,'Weekly Timesheet'!$B$14:$B$28,"Project",'Weekly Timesheet'!$D$14:$D$28,B72)),"") | N72: =IFERROR(IF(B72="","",SUMIFS('Weekly Timesheet'!$M$14:$M$28,'Weekly Timesheet'!$B$14:$B$28,"Project",'Weekly Timesheet'!$D$14:$D$28,B72)),"")
B73: {=IFERROR(INDEX(_xlfn._xlws.SORT(_xlfn.UNIQUE(_xlfn._xlws.FILTER('Weekly Timesheet'!$D$14:$D$28,'Weekly Timesheet'!$B$14:$B$28="Project"))),15),"")} | E73: {=IFERROR(IF(B73="","",INDEX('Weekly Timesheet'!$C$14:$C$28,MATCH(1,('Weekly Timesheet'!$B$14:$B$28="Project")*('Weekly Timesheet'!$D$14:$D$28=B73),0))),"")} | H73: =IFERROR(IF(B73="","",SUMIFS('Weekly Timesheet'!$E$14:$E$28,'Weekly Timesheet'!$B$14:$B$28,"Project",'Weekly Timesheet'!$D$14:$D$28,B73)),"") | I73: =IFERROR(IF(B73="","",SUMIFS('Weekly Timesheet'!$F$14:$F$28,'Weekly Timesheet'!$B$14:$B$28,"Project",'Weekly Timesheet'!$D$14:$D$28,B73)),"") | J73: =IFERROR(IF(B73="","",SUMIFS('Weekly Timesheet'!$G$14:$G$28,'Weekly Timesheet'!$B$14:$B$28,"Project",'Weekly Timesheet'!$D$14:$D$28,B73)),"") | K73: =IFERROR(IF(B73="","",SUMIFS('Weekly Timesheet'!$H$14:$H$28,'Weekly Timesheet'!$B$14:$B$28,"Project",'Weekly Timesheet'!$D$14:$D$28,B73)),"") | L73: =IFERROR(IF(B73="","",SUMIFS('Weekly Timesheet'!$I$14:$I$28,'Weekly Timesheet'!$B$14:$B$28,"Project",'Weekly Timesheet'!$D$14:$D$28,B73)),"") | M73: =IFERROR(IF(B73="","",SUMIFS('Weekly Timesheet'!$J$14:$J$28,'Weekly Timesheet'!$B$14:$B$28,"Project",'Weekly Timesheet'!$D$14:$D$28,B73)),"") | N73: =IFERROR(IF(B73="","",SUMIFS('Weekly Timesheet'!$M$14:$M$28,'Weekly Timesheet'!$B$14:$B$28,"Project",'Weekly Timesheet'!$D$14:$D$28,B73)),"")
B74: TOTAL PROJECT HOURS | H74: =IFERROR(SUMIF('Weekly Timesheet'!$B$14:$B$28,"Project",'Weekly Timesheet'!$E$14:$E$28),0) -> 8 | I74: =IFERROR(SUMIF('Weekly Timesheet'!$B$14:$B$28,"Project",'Weekly Timesheet'!$F$14:$F$28),0) -> 0 | J74: =IFERROR(SUMIF('Weekly Timesheet'!$B$14:$B$28,"Project",'Weekly Timesheet'!$G$14:$G$28),0) -> 0 | K74: =IFERROR(SUMIF('Weekly Timesheet'!$B$14:$B$28,"Project",'Weekly Timesheet'!$H$14:$H$28),0) -> 2 | L74: =IFERROR(SUMIF('Weekly Timesheet'!$B$14:$B$28,"Project",'Weekly Timesheet'!$I$14:$I$28),0) -> 0 | M74: =IFERROR(SUMIF('Weekly Timesheet'!$B$14:$B$28,"Project",'Weekly Timesheet'!$J$14:$J$28),0) -> 0 | N74: =IFERROR(SUMIF('Weekly Timesheet'!$B$14:$B$28,"Project",'Weekly Timesheet'!$M$14:$M$28),0) -> 10
B76: TIMESHEET ENTRY LOG
B78: # | C78: Main Category | D78: Sub-Category | E78: Project No. | F78: Mon | G78: Tue | H78: Wed | I78: Thu | J78: Fri | K78: Sat | L78: Sun | M78: Task Description | N78: Total hrs
B79: 1 | C79: =IFERROR(IF('Weekly Timesheet'!B14="","",'Weekly Timesheet'!B14),"") -> Admin | D79: =IFERROR(IF('Weekly Timesheet'!B14="","",'Weekly Timesheet'!C14),"") -> TIL Payout | E79: =IFERROR(IF('Weekly Timesheet'!B14="","",'Weekly Timesheet'!D14),"") -> 0 | F79: =IFERROR(IF('Weekly Timesheet'!B14="","",'Weekly Timesheet'!E14),"") -> 0 | G79: =IFERROR(IF('Weekly Timesheet'!B14="","",'Weekly Timesheet'!F14),"") -> 20 | H79: =IFERROR(IF('Weekly Timesheet'!B14="","",'Weekly Timesheet'!G14),"") -> 0 | I79: =IFERROR(IF('Weekly Timesheet'!B14="","",'Weekly Timesheet'!H14),"") -> 0 | J79: =IFERROR(IF('Weekly Timesheet'!B14="","",'Weekly Timesheet'!I14),"") -> 0 | K79: =IFERROR(IF('Weekly Timesheet'!B14="","",'Weekly Timesheet'!J14),"") -> 0 | L79: =IFERROR(IF('Weekly Timesheet'!B14="","",'Weekly Timesheet'!K14),"") -> 0 | M79: =IFERROR(IF('Weekly Timesheet'!C14="","",'Weekly Timesheet'!L14),"") -> Recived Payment | N79: =IFERROR(IF('Weekly Timesheet'!B14="","",'Weekly Timesheet'!M14),"") -> 20
B80: 2 | C80: =IFERROR(IF('Weekly Timesheet'!B15="","",'Weekly Timesheet'!B15),"") -> Project | D80: =IFERROR(IF('Weekly Timesheet'!B15="","",'Weekly Timesheet'!C15),"") -> Site Travel | E80: =IFERROR(IF('Weekly Timesheet'!B15="","",'Weekly Timesheet'!D15),"") -> 2026125 | F80: =IFERROR(IF('Weekly Timesheet'!B15="","",'Weekly Timesheet'!E15),"") -> 8 | G80: =IFERROR(IF('Weekly Timesheet'!B15="","",'Weekly Timesheet'!F15),"") -> 0 | H80: =IFERROR(IF('Weekly Timesheet'!B15="","",'Weekly Timesheet'!G15),"") -> 0 | I80: =IFERROR(IF('Weekly Timesheet'!B15="","",'Weekly Timesheet'!H15),"") -> 0 | J80: =IFERROR(IF('Weekly Timesheet'!B15="","",'Weekly Timesheet'!I15),"") -> 0 | K80: =IFERROR(IF('Weekly Timesheet'!B15="","",'Weekly Timesheet'!J15),"") -> 0 | L80: =IFERROR(IF('Weekly Timesheet'!B15="","",'Weekly Timesheet'!K15),"") -> 0 | M80: =IFERROR(IF('Weekly Timesheet'!C15="","",'Weekly Timesheet'!L15),"") -> Travel to YYC | N80: =IFERROR(IF('Weekly Timesheet'!B15="","",'Weekly Timesheet'!M15),"") -> 8
B81: 3 | C81: =IFERROR(IF('Weekly Timesheet'!B16="","",'Weekly Timesheet'!B16),"") -> Admin | D81: =IFERROR(IF('Weekly Timesheet'!B16="","",'Weekly Timesheet'!C16),"") -> Toolbox Meeting | E81: =IFERROR(IF('Weekly Timesheet'!B16="","",'Weekly Timesheet'!D16),"") -> 0 | F81: =IFERROR(IF('Weekly Timesheet'!B16="","",'Weekly Timesheet'!E16),"") -> 0 | G81: =IFERROR(IF('Weekly Timesheet'!B16="","",'Weekly Timesheet'!F16),"") -> 0 | H81: =IFERROR(IF('Weekly Timesheet'!B16="","",'Weekly Timesheet'!G16),"") -> 1 | I81: =IFERROR(IF('Weekly Timesheet'!B16="","",'Weekly Timesheet'!H16),"") -> 0 | J81: =IFERROR(IF('Weekly Timesheet'!B16="","",'Weekly Timesheet'!I16),"") -> 0 | K81: =IFERROR(IF('Weekly Timesheet'!B16="","",'Weekly Timesheet'!J16),"") -> 0 | L81: =IFERROR(IF('Weekly Timesheet'!B16="","",'Weekly Timesheet'!K16),"") -> 0 | M81: =IFERROR(IF('Weekly Timesheet'!C16="","",'Weekly Timesheet'!L16),"") -> Pit Stop | N81: =IFERROR(IF('Weekly Timesheet'!B16="","",'Weekly Timesheet'!M16),"") -> 1
B82: 4 | C82: =IFERROR(IF('Weekly Timesheet'!B17="","",'Weekly Timesheet'!B17),"") -> Office & Sales | D82: =IFERROR(IF('Weekly Timesheet'!B17="","",'Weekly Timesheet'!C17),"") -> General | E82: =IFERROR(IF('Weekly Timesheet'!B17="","",'Weekly Timesheet'!D17),"") -> 0 | F82: =IFERROR(IF('Weekly Timesheet'!B17="","",'Weekly Timesheet'!E17),"") -> 0 | G82: =IFERROR(IF('Weekly Timesheet'!B17="","",'Weekly Timesheet'!F17),"") -> 8 | H82: =IFERROR(IF('Weekly Timesheet'!B17="","",'Weekly Timesheet'!G17),"") -> 7 | I82: =IFERROR(IF('Weekly Timesheet'!B17="","",'Weekly Timesheet'!H17),"") -> 6 | J82: =IFERROR(IF('Weekly Timesheet'!B17="","",'Weekly Timesheet'!I17),"") -> 0 | K82: =IFERROR(IF('Weekly Timesheet'!B17="","",'Weekly Timesheet'!J17),"") -> 0 | L82: =IFERROR(IF('Weekly Timesheet'!B17="","",'Weekly Timesheet'!K17),"") -> 0 | M82: =IFERROR(IF('Weekly Timesheet'!C17="","",'Weekly Timesheet'!L17),"") -> Timesheet; Email Reply; Timesheet and Expense report template for Team | N82: =IFERROR(IF('Weekly Timesheet'!B17="","",'Weekly Timesheet'!M17),"") -> 21
B83: 5 | C83: =IFERROR(IF('Weekly Timesheet'!B18="","",'Weekly Timesheet'!B18),"") -> Project | D83: =IFERROR(IF('Weekly Timesheet'!B18="","",'Weekly Timesheet'!C18),"") -> Report | E83: =IFERROR(IF('Weekly Timesheet'!B18="","",'Weekly Timesheet'!D18),"") -> 2026125 | F83: =IFERROR(IF('Weekly Timesheet'!B18="","",'Weekly Timesheet'!E18),"") -> 0 | G83: =IFERROR(IF('Weekly Timesheet'!B18="","",'Weekly Timesheet'!F18),"") -> 0 | H83: =IFERROR(IF('Weekly Timesheet'!B18="","",'Weekly Timesheet'!G18),"") -> 0 | I83: =IFERROR(IF('Weekly Timesheet'!B18="","",'Weekly Timesheet'!H18),"") -> 2 | J83: =IFERROR(IF('Weekly Timesheet'!B18="","",'Weekly Timesheet'!I18),"") -> 0 | K83: =IFERROR(IF('Weekly Timesheet'!B18="","",'Weekly Timesheet'!J18),"") -> 0 | L83: =IFERROR(IF('Weekly Timesheet'!B18="","",'Weekly Timesheet'!K18),"") -> 0 | M83: =IFERROR(IF('Weekly Timesheet'!C18="","",'Weekly Timesheet'!L18),"") -> Summary Letter | N83: =IFERROR(IF('Weekly Timesheet'!B18="","",'Weekly Timesheet'!M18),"") -> 2
B84: 6 | C84: =IFERROR(IF('Weekly Timesheet'!B19="","",'Weekly Timesheet'!B19),"") -> Admin | D84: =IFERROR(IF('Weekly Timesheet'!B19="","",'Weekly Timesheet'!C19),"") -> Statutory Holiday | E84: =IFERROR(IF('Weekly Timesheet'!B19="","",'Weekly Timesheet'!D19),"") -> 0 | F84: =IFERROR(IF('Weekly Timesheet'!B19="","",'Weekly Timesheet'!E19),"") -> 0 | G84: =IFERROR(IF('Weekly Timesheet'!B19="","",'Weekly Timesheet'!F19),"") -> 0 | H84: =IFERROR(IF('Weekly Timesheet'!B19="","",'Weekly Timesheet'!G19),"") -> 0 | I84: =IFERROR(IF('Weekly Timesheet'!B19="","",'Weekly Timesheet'!H19),"") -> 0 | J84: =IFERROR(IF('Weekly Timesheet'!B19="","",'Weekly Timesheet'!I19),"") -> 8 | K84: =IFERROR(IF('Weekly Timesheet'!B19="","",'Weekly Timesheet'!J19),"") -> 0 | L84: =IFERROR(IF('Weekly Timesheet'!B19="","",'Weekly Timesheet'!K19),"") -> 0 | M84: =IFERROR(IF('Weekly Timesheet'!C19="","",'Weekly Timesheet'!L19),"") -> Good Friday | N84: =IFERROR(IF('Weekly Timesheet'!B19="","",'Weekly Timesheet'!M19),"") -> 8
B85: 7 | C85: =IFERROR(IF('Weekly Timesheet'!B20="","",'Weekly Timesheet'!B20),"") | D85: =IFERROR(IF('Weekly Timesheet'!B20="","",'Weekly Timesheet'!C20),"") | E85: =IFERROR(IF('Weekly Timesheet'!B20="","",'Weekly Timesheet'!D20),"") | F85: =IFERROR(IF('Weekly Timesheet'!B20="","",'Weekly Timesheet'!E20),"") | G85: =IFERROR(IF('Weekly Timesheet'!B20="","",'Weekly Timesheet'!F20),"") | H85: =IFERROR(IF('Weekly Timesheet'!B20="","",'Weekly Timesheet'!G20),"") | I85: =IFERROR(IF('Weekly Timesheet'!B20="","",'Weekly Timesheet'!H20),"") | J85: =IFERROR(IF('Weekly Timesheet'!B20="","",'Weekly Timesheet'!I20),"") | K85: =IFERROR(IF('Weekly Timesheet'!B20="","",'Weekly Timesheet'!J20),"") | L85: =IFERROR(IF('Weekly Timesheet'!B20="","",'Weekly Timesheet'!K20),"") | M85: =IFERROR(IF('Weekly Timesheet'!C20="","",'Weekly Timesheet'!L20),"") | N85: =IFERROR(IF('Weekly Timesheet'!B20="","",'Weekly Timesheet'!M20),"")
B86: 8 | C86: =IFERROR(IF('Weekly Timesheet'!B21="","",'Weekly Timesheet'!B21),"") | D86: =IFERROR(IF('Weekly Timesheet'!B21="","",'Weekly Timesheet'!C21),"") | E86: =IFERROR(IF('Weekly Timesheet'!B21="","",'Weekly Timesheet'!D21),"") | F86: =IFERROR(IF('Weekly Timesheet'!B21="","",'Weekly Timesheet'!E21),"") | G86: =IFERROR(IF('Weekly Timesheet'!B21="","",'Weekly Timesheet'!F21),"") | H86: =IFERROR(IF('Weekly Timesheet'!B21="","",'Weekly Timesheet'!G21),"") | I86: =IFERROR(IF('Weekly Timesheet'!B21="","",'Weekly Timesheet'!H21),"") | J86: =IFERROR(IF('Weekly Timesheet'!B21="","",'Weekly Timesheet'!I21),"") | K86: =IFERROR(IF('Weekly Timesheet'!B21="","",'Weekly Timesheet'!J21),"") | L86: =IFERROR(IF('Weekly Timesheet'!B21="","",'Weekly Timesheet'!K21),"") | M86: =IFERROR(IF('Weekly Timesheet'!C21="","",'Weekly Timesheet'!L21),"") | N86: =IFERROR(IF('Weekly Timesheet'!B21="","",'Weekly Timesheet'!M21),"")
B87: 9 | C87: =IFERROR(IF('Weekly Timesheet'!B22="","",'Weekly Timesheet'!B22),"") | D87: =IFERROR(IF('Weekly Timesheet'!B22="","",'Weekly Timesheet'!C22),"") | E87: =IFERROR(IF('Weekly Timesheet'!B22="","",'Weekly Timesheet'!D22),"") | F87: =IFERROR(IF('Weekly Timesheet'!B22="","",'Weekly Timesheet'!E22),"") | G87: =IFERROR(IF('Weekly Timesheet'!B22="","",'Weekly Timesheet'!F22),"") | H87: =IFERROR(IF('Weekly Timesheet'!B22="","",'Weekly Timesheet'!G22),"") | I87: =IFERROR(IF('Weekly Timesheet'!B22="","",'Weekly Timesheet'!H22),"") | J87: =IFERROR(IF('Weekly Timesheet'!B22="","",'Weekly Timesheet'!I22),"") | K87: =IFERROR(IF('Weekly Timesheet'!B22="","",'Weekly Timesheet'!J22),"") | L87: =IFERROR(IF('Weekly Timesheet'!B22="","",'Weekly Timesheet'!K22),"") | M87: =IFERROR(IF('Weekly Timesheet'!C22="","",'Weekly Timesheet'!L22),"") | N87: =IFERROR(IF('Weekly Timesheet'!B22="","",'Weekly Timesheet'!M22),"")
B88: 10 | C88: =IFERROR(IF('Weekly Timesheet'!B23="","",'Weekly Timesheet'!B23),"") | D88: =IFERROR(IF('Weekly Timesheet'!B23="","",'Weekly Timesheet'!C23),"") | E88: =IFERROR(IF('Weekly Timesheet'!B23="","",'Weekly Timesheet'!D23),"") | F88: =IFERROR(IF('Weekly Timesheet'!B23="","",'Weekly Timesheet'!E23),"") | G88: =IFERROR(IF('Weekly Timesheet'!B23="","",'Weekly Timesheet'!F23),"") | H88: =IFERROR(IF('Weekly Timesheet'!B23="","",'Weekly Timesheet'!G23),"") | I88: =IFERROR(IF('Weekly Timesheet'!B23="","",'Weekly Timesheet'!H23),"") | J88: =IFERROR(IF('Weekly Timesheet'!B23="","",'Weekly Timesheet'!I23),"") | K88: =IFERROR(IF('Weekly Timesheet'!B23="","",'Weekly Timesheet'!J23),"") | L88: =IFERROR(IF('Weekly Timesheet'!B23="","",'Weekly Timesheet'!K23),"") | M88: =IFERROR(IF('Weekly Timesheet'!C23="","",'Weekly Timesheet'!L23),"") | N88: =IFERROR(IF('Weekly Timesheet'!B23="","",'Weekly Timesheet'!M23),"")
B89: 11 | C89: =IFERROR(IF('Weekly Timesheet'!B24="","",'Weekly Timesheet'!B24),"") | D89: =IFERROR(IF('Weekly Timesheet'!B24="","",'Weekly Timesheet'!C24),"") | E89: =IFERROR(IF('Weekly Timesheet'!B24="","",'Weekly Timesheet'!D24),"") | F89: =IFERROR(IF('Weekly Timesheet'!B24="","",'Weekly Timesheet'!E24),"") | G89: =IFERROR(IF('Weekly Timesheet'!B24="","",'Weekly Timesheet'!F24),"") | H89: =IFERROR(IF('Weekly Timesheet'!B24="","",'Weekly Timesheet'!G24),"") | I89: =IFERROR(IF('Weekly Timesheet'!B24="","",'Weekly Timesheet'!H24),"") | J89: =IFERROR(IF('Weekly Timesheet'!B24="","",'Weekly Timesheet'!I24),"") | K89: =IFERROR(IF('Weekly Timesheet'!B24="","",'Weekly Timesheet'!J24),"") | L89: =IFERROR(IF('Weekly Timesheet'!B24="","",'Weekly Timesheet'!K24),"") | M89: =IFERROR(IF('Weekly Timesheet'!C24="","",'Weekly Timesheet'!L24),"") | N89: =IFERROR(IF('Weekly Timesheet'!B24="","",'Weekly Timesheet'!M24),"")
B90: 12 | C90: =IFERROR(IF('Weekly Timesheet'!B25="","",'Weekly Timesheet'!B25),"") | D90: =IFERROR(IF('Weekly Timesheet'!B25="","",'Weekly Timesheet'!C25),"") | E90: =IFERROR(IF('Weekly Timesheet'!B25="","",'Weekly Timesheet'!D25),"") | F90: =IFERROR(IF('Weekly Timesheet'!B25="","",'Weekly Timesheet'!E25),"") | G90: =IFERROR(IF('Weekly Timesheet'!B25="","",'Weekly Timesheet'!F25),"") | H90: =IFERROR(IF('Weekly Timesheet'!B25="","",'Weekly Timesheet'!G25),"") | I90: =IFERROR(IF('Weekly Timesheet'!B25="","",'Weekly Timesheet'!H25),"") | J90: =IFERROR(IF('Weekly Timesheet'!B25="","",'Weekly Timesheet'!I25),"") | K90: =IFERROR(IF('Weekly Timesheet'!B25="","",'Weekly Timesheet'!J25),"") | L90: =IFERROR(IF('Weekly Timesheet'!B25="","",'Weekly Timesheet'!K25),"") | M90: =IFERROR(IF('Weekly Timesheet'!C25="","",'Weekly Timesheet'!L25),"") | N90: =IFERROR(IF('Weekly Timesheet'!B25="","",'Weekly Timesheet'!M25),"")
... B93: 15 | C93: =IFERROR(IF('Weekly Timesheet'!B28="","",'Weekly Timesheet'!B28),"") | D93: =IFERROR(IF('Weekly Timesheet'!B28="","",'Weekly Timesheet'!C28),"") | E93: =IFERROR(IF('Weekly Timesheet'!B28="","",'Weekly Timesheet'!D28),"") | F93: =IFERROR(IF('Weekly Timesheet'!B28="","",'Weekly Timesheet'!E28),"") | G93: =IFERROR(IF('Weekly Timesheet'!B28="","",'Weekly Timesheet'!F28),"") | H93: =IFERROR(IF('Weekly Timesheet'!B28="","",'Weekly Timesheet'!G28),"") | I93: =IFERROR(IF('Weekly Timesheet'!B28="","",'Weekly Timesheet'!H28),"") | J93: =IFERROR(IF('Weekly Timesheet'!B28="","",'Weekly Timesheet'!I28),"") | K93: =IFERROR(IF('Weekly Timesheet'!B28="","",'Weekly Timesheet'!J28),"") | L93: =IFERROR(IF('Weekly Timesheet'!B28="","",'Weekly Timesheet'!K28),"") | M93: =IFERROR(IF('Weekly Timesheet'!C28="","",'Weekly Timesheet'!L28),"") | N93: =IFERROR(IF('Weekly Timesheet'!B28="","",'Weekly Timesheet'!M28),"")
B94: WEEK TOTALS | F94: =IFERROR(SUM('Weekly Timesheet'!E14:E28),0) -> 8 | G94: =IFERROR(SUM('Weekly Timesheet'!F14:F28),0) -> 28 | H94: =IFERROR(SUM('Weekly Timesheet'!G14:G28),0) -> 8 | I94: =IFERROR(SUM('Weekly Timesheet'!H14:H28),0) -> 8 | J94: =IFERROR(SUM('Weekly Timesheet'!I14:I28),0) -> 8 | K94: =IFERROR(SUM('Weekly Timesheet'!J14:J28),0) -> 0 | L94: =IFERROR(SUM('Weekly Timesheet'!K14:K28),0) -> 0 | N94: =IFERROR(SUM('Weekly Timesheet'!M14:M28),0) -> 60
B96: ⓘ All data pulls automatically from the Weekly Timesheet. Read-only — edit source data in the Weekly Timesheet tab only. Project breakdown shows each unique project number exactly once.

Sheet 📊 TIL Summary
B2: 📊 TIL (Time in Lieu) TRACKING SUMMARY
B4: Week Starting | C4: Opening Balance (hrs) | D4: Overtime Earned | E4: TIL Used (Taken) | F4: Closing Balance | G4: Approver
B5: 46111 | C5: 843.25 | D5: ='Weekly Timesheet'!I9 -> 0 | E5: ='Weekly Timesheet'!N29 -> 20 | F5: =C5+D5-E5 -> 823.25 | G5: AH
B7: 💡 Instructions: Enter week start date in column B. Negative values in column E represent TIL taken. Row 5 opening balance = your historical TIL carry-forward (enter manually).

Sheet 🏖 Vacation Summary
B2: 🏖 VACATION HOURS TRACKING SUMMARY
B4: ANNUAL VACATION ALLOCATION BY POSITION
B5: Position | C5: Annual Vacation (hrs) | D5: Equivalent Days (8 hrs/day) | E5: Notes
B6: Process Engineer EIT | C6: 120 | D6: 15
B7: Admin | C7: 200 | D7: =C7/8 -> 25
B8: Senior Engineer | C8: 200 | D8: =C8/8 -> 25
B9: Sales & Marketing | C9: 160 | D9: =C9/8 -> 20
B11: WEEKLY VACATION TRACKING
B12: Week Starting | C12: Opening Balance (hrs) | D12: Vacation Used This Week | E12: Closing Balance (hrs) | F12: Approver | G12: Notes
B13: 46104 | C13: 48 | D13: ='Weekly Timesheet'!I10 -> 0 | E13: =IF(C13="","",C13-D13) -> 48
E14: =IF(C14="","",C14-D14)
E15: =IF(C15="","",C15-D15)
E16: =IF(C16="","",C16-D16)
E17: =IF(C17="","",C17-D17)
E18: =IF(C18="","",C18-D18)
E19: =IF(C19="","",C19-D19)
E20: =IF(C20="","",C20-D20)
E21: =IF(C21="","",C21-D21)
E22: =IF(C22="","",C22-D22)
E23: =IF(C23="","",C23-D23)
E24: =IF(C24="","",C24-D24)
B26: 💡 Row 14 Opening Balance = employee's current vacation bank. Update each week: new Opening = prior week Closing Balance. Vacation Used pulls automatically from the Weekly Timesheet.

Sheet 📁 Approval Log
B2: 📁 TIMESHEET APPROVAL LOG – ADMIN USE ONLY
B4: # | C4: Employee Name | D4: Employee ID | E4: Week Starting | F4: Submitted Date | G4: Status | H4: Action By (Admin) | I4: Action Date/Time | J4: Comments / Reason for Decline
B5: 1
B6: 2
B7: 3
B8: 4
B9: 5
B10: 6
B11: 7
B12: 8
B13: 9
B14: 10
B15: 11
B16: 12
... B104: 100
B106: 🔐 ADMIN INSTRUCTIONS: 1) When employee submits timesheet, add a row here. 2) Set Status to 'Approved' or 'Declined'. 3) Enter your name in 'Action By' and today's date in 'Action Date/Time'. 4) For Declined entries, provide a clear reason in Comments. 5) Approved timesheets must not be edited — notify employee to resubmit if error found.

Sheet 🗂 Reference Data
A1: Main Category | B1: Project Sub-Cat | C1: Admin Sub-Cat | D1: Office Sub-Cat | E1: Status Options | F1: All Sub-Categories
A2: Project | B2: Travel | C2: Overtime Taken | D2: Customer Contact | E2: Draft | F2: Travel
A3: Admin | B3: Site Travel | C3: TIL Payout | D3: Project Development | E3: Submitted | F3: Site Travel
A4: Office & Sales | B4: Site Work | C4: Sick Time | D4: Proposals & Quotes | E4: Approved | F4: Site Work
B5: Report | C5: Vacation Hours | D5: Inventory | E5: Declined | F5: Report
B6: Extra Integration | C6: Statutory Holiday | D6: SRU Study | F6: Extra Integration
B7: Simulation | C7: Administrative | D7: Conference | F7: Simulation
B8: Office Preparation | C8: Toolbox Meeting | D8: General | F8: Office Preparation
B9: Project Management | F9: Project Management
B10: Engineering Work | F10: Engineering Work
F11: Overtime Taken
F12: TIL Payout
F13: Sick Time
F14: Vacation Hours
F15: Statutory Holiday
F16: Administrative
F17: Toolbox Meeting
F18: Customer Contact
F19: Project Development
F20: Proposals & Quotes
F21: Inventory
F22: SRU Study
... F24: General
